Workbook

Sheet Data
A1: Data Source | B1: World Development Indicators
A2: Last Updated Date | B2: 46303
A4: Country Name | B4: Country Code | C4: Indicator Name | D4: Indicator Code | E4: 1960 | F4: 1961 | G4: 1962 | H4: 1963 | I4: 1964 | J4: 1965 | K4: 1966 | L4: 1967 | M4: 1968 | N4: 1969 | O4: 1970 | P4: 1971 | Q4: 1972 | R4: 1973 | S4: 1974 | T4: 1975 | U4: 1976 | V4: 1977 | W4: 1978 | X4: 1979 | Y4: 1980 | Z4: 1981 | AA4: 1982 | AB4: 1983 | AC4: 1984 | AD4: 1985 | AE4: 1986 | AF4: 1987 | AG4: 1988 | AH4: 1989 | AI4: 1990 | AJ4: 1991 | AK4: 1992 | AL4: 1993 | AM4: 1994 | AN4: 1995 | AO4: 1996 | AP4: 1997 | AQ4: 1998 | AR4: 1999 | AS4: 2000 | AT4: 2001 | AU4: 2002 | AV4: 2003 | AW4: 2004 | AX4: 2005 | AY4: 2006 | AZ4: 2007 | BA4: 2008 | BB4: 2009 | BC4: 2010 | BD4: 2011 | BE4: 2012 | BF4: 2013 | BG4: 2014 | BH4: 2015 | BI4: 2016 | BJ4: 2017 | BK4: 2018 | BL4: 2019 | BM4: 2020 | BN4: 2021 | BO4: 2022 | BP4: 2023 | BQ4: 2024 | BR4: 2025
A5: Aruba | B5: ABW | C5: Individuals using the Internet (% of population) | D5: IT.NET.USER.ZS | AI5: 0 | AO5: 2.77 | AR5: 4.51 | AS5: 15.442823 | AT5: 17.1 | AU5: 18.8 | AV5: 20.8 | AW5: 23 | AX5: 25.4 | AY5: 28 | AZ5: 30.9 | BA5: 52 | BB5: 58 | BC5: 62 | BD5: 69 | BE5: 74 | BF5: 78.9 | BG5: 83.78 | BH5: 88.661227 | BI5: 93.542454 | BJ5: 97.17
A6: Africa Eastern and Southern | B6: AFE | C6: Individuals using the Internet (% of population) | D6: IT.NET.USER.ZS | AX6: 1.8 | AY6: 1.9 | AZ6: 2.7 | BA6: 3 | BB6: 3.5 | BC6: 5.3 | BD6: 6.8 | BE6: 8.4 | BF6: 10 | BG6: 12.1 | BH6: 14.3 | BI6: 16.3 | BJ6: 17.3 | BK6: 19.6 | BL6: 21.6 | BM6: 23.5 | BN6: 25 | BO6: 26.8 | BP6: 27.8 | BQ6: 28.8 | BR6: 30.4
A7: Afghanistan | B7: AFG | C7: Individuals using the Internet (% of population) | D7: IT.NET.USER.ZS | AI7: 0 | AT7: 0.0047225682 | AU7: 0.0045613952 | AV7: 0.087891253 | AW7: 0.10580903 | AX7: 1.2241481 | AY7: 2.1071236 | AZ7: 1.9 | BA7: 1.84 | BB7: 3.55 | BC7: 4 | BD7: 5 | BE7: 5.4545002 | BF7: 5.9000001 | BG7: 7 | BH7: 8.2600002 | BI7: 11 | BJ7: 13.5 | BK7: 16.799999 | BL7: 17.6 | BM7: 17.0485 | BN7: 16.514299 | BO7: 15.8663 | BP7: 15.9284 | BQ7: 16.094999
A8: Africa Western and Central | B8: AFW | C8: Individuals using the Internet (% of population) | D8: IT.NET.USER.ZS | AX8: 2.3 | AY8: 3.4 | AZ8: 4.3 | BA8: 5 | BB8: 5.8 | BC8: 7.3 | BD8: 8.7 | BE8: 10.3 | BF8: 12.6 | BG8: 15 | BH8: 18.6 | BI8: 20.9 | BJ8: 23.8 | BK8: 25.7 | BL8: 28.5 | BM8: 31.5 | BN8: 34.7 | BO8: 37.5 | BP8: 38.5 | BQ8: 40 | BR8: 42.4
A9: Angola | B9: AGO | C9: Individuals using the Internet (% of population) | D9: IT.NET.USER.ZS | AI9: 0 | AO9: 0.000776 | AP9: 0.00567 | AQ9: 0.0185 | AR9: 0.072 | AS9: 0.10504556 | AT9: 0.13601387 | AU9: 0.27037675 | AV9: 0.37068207 | AW9: 0.46481462 | AX9: 1.1434 | AY9: 1.5 | AZ9: 1.7 | BA9: 1.9 | BB9: 2.3 | BC9: 2.8 | BD9: 4.6999998 | BE9: 7.6999998 | BF9: 13 | BG9: 21.362341 | BH9: 22 | BI9: 23.200001 | BJ9: 26 | BK9: 29 | BL9: 32.129398 | BM9: 33.3209 | BN9: 34.556499 | BO9: 35.838001 | BP9: 37.885899 | BQ9: 40.7048
A10: Albania | B10: ALB | C10: Individuals using the Internet (% of population) | D10: IT.NET.USER.ZS | AI10: 0 | AN10: 0.0112 | AO10: 0.0322 | AP10: 0.0486 | AQ10: 0.065 | AR10: 0.0814 | AS10: 0.11409735 | AT10: 0.32579838 | AU10: 0.39008127 | AV10: 0.97190042 | AW10: 2.4203878 | AX10: 6.0438909 | AY10: 9.6099997 | AZ10: 15.0361 | BA10: 23.86 | BB10: 41.2 | BC10: 45 | BD10: 47 | BE10: 49.400002 | BF10: 51.799999 | BG10: 54.299999 | BH10: 56.900002 | BI10: 59.599998 | BJ10: 62.400002 | BK10: 65.400002 | BL10: 68.550391 | BM10: 72.237677 | BN10: 79.323718 | BO10: 82.613675 | BP10: 83.135592 | BQ10: 85.863899
A11: Andorra | B11: AND | C11: Individuals using the Internet (% of population) | D11: IT.NET.USER.ZS | AI11: 0 | AO11: 1.53 | AP11: 3.05 | AQ11: 6.89 | AR11: 7.64 | AS11: 10.538836 | AU11: 11.260469 | AV11: 13.546413 | AW11: 26.837954 | AX11: 37.605766 | AY11: 48.936847 | AZ11: 70.87 | BA11: 70.04 | BB11: 78.53 | BC11: 81 | BD11: 81 | BE11: 82.699997 | BF11: 84.400002 | BG11: 86.099998 | BH11: 87.900002 | BI11: 89.699997 | BJ11: 91.567467 | BK11: 93.5 | BL11: 90.718697 | BM11: 93.205704 | BN11: 93.897499 | BO11: 94.051697 | BP11: 94.214996 | BQ11: 94.397598
A12: Arab World | B12: ARB | C12: Individuals using the Internet (% of population) | D12: IT.NET.USER.ZS
A13: United Arab Emirates | B13: ARE | C13: Individuals using the Internet (% of population) | D13: IT.NET.USER.ZS | AI13: 0 | AN13: 0.103 | AO13: 0.375 | AP13: 3.3 | AQ13: 6.91 | AR13: 14.9 | AS13: 23.625301 | AT13: 26.271754 | AU13: 28.316485 | AV13: 29.477953 | AW13: 30.131296 | AX13: 40 | AY13: 52 | AZ13: 61 | BA13: 63 | BB13: 64 | BC13: 68 | BD13: 78 | BE13: 84.999992 | BF13: 88 | BG13: 90.400011 | BH13: 90.5 | BI13: 90.600007 | BJ13: 94.819923 | BK13: 98.450002 | BL13: 99.149998 | BM13: 100 | BN13: 100 | BO13: 100 | BP13: 100 | BQ13: 100
A14: Argentina | B14: ARG | C14: Individuals using the Internet (% of population) | D14: IT.NET.USER.ZS | AI14: 0 | AK14: 0.00299 | AL14: 0.0295 | AM14: 0.0437 | AN14: 0.0863 | AO14: 0.142 | AP14: 0.28 | AQ14: 0.831 | AR14: 3.28 | AS14: 7.0386831 | AT14: 9.7808073 | AU14: 10.882124 | AV14: 11.913697 | AW14: 16.036684 | AX14: 17.720583 | AY14: 20.927202 | AZ14: 25.946633 | BA14: 28.112623 | BB14: 34 | BC14: 45 | BD14: 51 | BE14: 55.799999 | BF14: 59.900002 | BG14: 64.699997 | BH14: 68.043064 | BI14: 70.968981 | BJ14: 74.294907 | BK14: 77.7 | BL14: 79.946952 | BM14: 85.514386 | BN14: 87.150707 | BO14: 88.375357 | BP14: 89.228972 | BQ14: 89.667152
A15: Armenia | B15: ARM | C15: Individuals using the Internet (% of population) | D15: IT.NET.USER.ZS | AI15: 0 | AM15: 0.00912 | AN15: 0.0527 | AO15: 0.0946 | AP15: 0.112 | AQ15: 0.129 | AR15: 0.971 | AS15: 1.30047 | AT15: 1.6310947 | AU15: 1.960405 | AV15: 4.5752172 | AW15: 4.8990086 | AX15: 5.2529998 | AY15: 5.6318002 | AZ15: 6.0212998 | BA15: 6.21 | BB15: 15.3 | BC15: 25 | BD15: 32 | BE15: 37.5 | BF15: 41.9 | BG15: 54.622806 | BH15: 59.100834 | BI15: 64.34603 | BJ15: 64.744884 | BK15: 68.245052 | BL15: 66.54395 | BM15: 76.507701 | BN15: 78.612258 | BO15: 77.027675 | BP15: 79.99663 | BQ15: 81.339302
A16: American Samoa | B16: ASM | C16: Individuals using the Internet (% of population) | D16: IT.NET.USER.ZS | AI16: 0
A17: Antigua and Barbuda | B17: ATG | C17: Individuals using the Internet (% of population) | D17: IT.NET.USER.ZS | AI17: 0 | AN17: 2.2 | AO17: 2.86 | AP17: 3.48 | AQ17: 4.07 | AR17: 5.3 | AS17: 6.4822257 | AT17: 8.8992855 | AU17: 12.5 | AV17: 17.228649 | AW17: 24.266544 | AX17: 27 | AY17: 30 | AZ17: 34 | BA17: 38 | BB17: 42 | BC17: 47 | BD17: 52 | BE17: 58 | BF17: 63.400002 | BG17: 67.779999 | BH17: 70 | BI17: 70.271599 | BJ17: 70.544197 | BK17: 70.817902 | BL17: 71.092598 | BM17: 71.368401 | BN17: 71.645302 | BO17: 71.923302 | BP17: 72.1241 | BQ17: 72.7304
A18: Australia | B18: AUS | C18: Individuals using the Internet (% of population) | D18: IT.NET.USER.ZS | AI18: 0.585 | AJ18: 1.1 | AK18: 1.77 | AL18: 1.97 | AM18: 2.23 | AN18: 2.76 | AO18: 3.28 | AP18: 16.4 | AQ18: 30.8 | AR18: 40.8 | AS18: 46.756116 | AT18: 52.689266 | AX18: 63 | AY18: 66 | AZ18: 69.45 | BA18: 71.67 | BB18: 74.25 | BC18: 76 | BD18: 79.487698 | BE18: 79 | BF18: 83.453497 | BG18: 84 | BH18: 84.560515 | BI18: 86.540001 | BJ18: 86.545049 | BK18: 90.008202 | BL18: 93.609901 | BM18: 94.693497 | BN18: 96.972198 | BO18: 96.1194 | BP18: 96.116096 | BQ18: 96.131401
A19: Austria | B19: AUT | C19: Individuals using the Internet (% of population) | D19: IT.NET.USER.ZS | AI19: 0.13 | AJ19: 0.259 | AK19: 0.643 | AL19: 0.765 | AM19: 1.39 | AN19: 1.89 | AO19: 6.91 | AP19: 9.53 | AQ19: 15.4 | AR19: 23 | AS19: 33.730133 | AT19: 39.18545 | AU19: 36.56 | AV19: 42.7 | AW19: 54.28 | AX19: 58 | AY19: 63.6 | AZ19: 69.37 | BA19: 72.87 | BB19: 73.45 | BC19: 75.17 | BD19: 78.739993 | BE19: 80.029994 | BF19: 80.6188 | BG19: 80.995825 | BH19: 83.940142 | BI19: 84.323743 | BJ19: 87.935587 | BK19: 87.479137 | BL19: 87.752205 | BM19: 87.529428 | BN19: 92.529151 | BO19: 93.614091 | BP19: 95.334671 | BQ19: 94.919749 | BR19: 91.925734
A20: Azerbaijan | B20: AZE | C20: Individuals using the Internet (% of population) | D20: IT.NET.USER.ZS | AI20: 0 | AM20: 0.00143 | AN20: 0.00206 | AO20: 0.00635 | AP20: 0.0252 | AQ20: 0.0375 | AR20: 0.0992 | AS20: 0.14775758 | AT20: 0.30556464 | AU20: 4.9997137 | AX20: 8.0304003 | AY20: 11.9922 | AZ20: 14.54 | BA20: 17.08 | BB20: 27.4 | BC20: 46 | BD20: 50 | BE20: 54.200001 | BF20: 73.000001 | BG20: 75.000016 | BH20: 77 | BI20: 78.2 | BJ20: 79 | BK20: 79.799995 | BL20: 81.099999 | BM20: 84.599996 | BN20: 85.99999 | BO20: 88 | BP20: 89 | BQ20: 90.439796 | BR20: 90.800002
A21: Burundi | B21: BDI | C21: Individuals using the Internet (% of population) | D21: IT.NET.USER.ZS | AI21: 0 | AJ21: 0 | AK21: 0 | AL21: 0 | AM21: 0 | AN21: 0 | AO21: 0.000804 | AP21: 0.00798 | AQ21: 0.0158 | AR21: 0.0392 | AS21: 0.077248447 | AT21: 0.10600125 | AU21: 0.11822841 | AV21: 0.2012732 | AW21: 0.34906046 | AX21: 0.54210001 | AY21: 0.65759999 | AZ21: 0.7 | BA21: 0.81 | BB21: 0.89999998 | BC21: 1 | BD21: 1.11 | BE21: 1.22 | BF21: 1.2642181 | BG21: 1.0423921 | BH21: 2 | BI21: 2.2 | BJ21: 2.6607485 | BK21: 4.0194998 | BL21: 6.0721998 | BM21: 6.4301 | BN21: 6.7779999 | BO21: 7.1448002 | BP21: 7.1722999 | BQ21: 8.5959997
A22: Belgium | B22: BEL | C22: Individuals using the Internet (% of population) | D22: IT.NET.USER.ZS | AI22: 0.00101 | AJ22: 0.0201 | AK22: 0.1 | AL22: 0.199 | AM22: 0.696 | AN22: 0.992 | AO22: 2.97 | AP22: 4.94 | AQ22: 7.89 | AR22: 13.8 | AS22: 29.431692 | AT22: 31.288396 | AU22: 46.33 | AV22: 49.97 | AW22: 53.86 | AX22: 55.82 | AY22: 61.98187 | AZ22: 66.76042 | BA22: 68.857322 | BB22: 74.544146 | BC22: 77.639786 | BD22: 81.609996 | BE22: 80.719991 | BF22: 82.1702 | BG22: 85.001238 | BH22: 85.052942 | BI22: 86.516477 | BJ22: 87.679681 | BK22: 88.647343 | BL22: 90.275428 | BM22: 91.526416 | BN22: 92.788676 | BO22: 94.007831 | BP22: 94.626251 | BQ22: 95.775791
A23: Benin | B23: BEN | C23: Individuals using the Internet (% of population) | D23: IT.NET.USER.ZS | AI23: 0 | AO23: 0.00169 | AP23: 0.0246 | AQ23: 0.0479 | AR23: 0.155 | AS23: 0.22524785 | AT23: 0.36341789 | AU23: 0.7029456 | AV23: 0.95132711 | AW23: 1.182541 | AX23: 1.271 | AY23: 1.5379 | AZ23: 1.79 | BA23: 1.85 | BB23: 2.24 | BC23: 3.13 | BD23: 4.1483231 | BE23: 4.5 | BF23: 4.9000001 | BG23: 6 | BH23: 11.255 | BI23: 14.5 | BJ23: 18.7 | BK23: 19 | BL23: 20.500999 | BM23: 22.1206 | BN23: 28.2047 | BO23: 30.5373 | BP23: 32.394001 | BQ23: 33.983799
A24: Burkina Faso | B24: BFA | C24: Individuals using the Internet (% of population) | D24: IT.NET.USER.ZS | AI24: 0 | AO24: 0.000961 | AP24: 0.0187 | AQ24: 0.0454 | AR24: 0.0618 | AS24: 0.077080169 | AT24: 0.15773246 | AU24: 0.2009926 | AV24: 0.3734403 | AW24: 0.40029529 | AX24: 0.46990001 | AY24: 0.63270003 | AZ24: 0.75 | BA24: 0.92000002 | BB24: 1.13 | BC24: 2.4000001 | BD24: 3 | BE24: 3.7249999 | BF24: 5 | BG24: 6 | BH24: 6.5457001 | BI24: 7.1409998 | BJ24: 7.7904 | BK24: 8.4989004 | BL24: 9.271806 | BM24: 12.9732 | BN24: 18.152201 | BO24: 25.3988 | BP24: 25.3612 | BQ24: 28.252701
A25: Bangladesh | B25: BGD | C25: Individuals using the Internet (% of population) | D25: IT.NET.USER.ZS | AI25: 0 | AP25: 0.000751 | AQ25: 0.00368 | AR25: 0.0362 | AS25: 0.071039423 | AT25: 0.12980797 | AU25: 0.13992029 | AV25: 0.16387767 | AW25: 0.19903633 | AX25: 0.24160001 | AY25: 1 | AZ25: 1.8 | BA25: 2.5 | BB25: 3.0999999 | BC25: 3.7 | BD25: 4.5 | BE25: 5 | BF25: 6.63 | BG25: 9.0529003 | BH25: 12.3688 | BI25: 16.899099 | BJ25: 21.5 | BK25: 25.5651 | BL25: 30.383101 | BM25: 36.1091 | BN25: 38.917445 | BO25: 41.616501 | BP25: 44.502742 | BQ25: 53.421713
A26: Bulgaria | B26: BGR | C26: Individuals using the Internet (% of population) | D26: IT.NET.USER.ZS | AI26: 0 | AL26: 0.00234 | AM26: 0.0195 | AN26: 0.12 | AO26: 0.725 | AP26: 1.22 | AQ26: 1.84 | AR26: 2.91 | AS26: 5.3709235 | AT26: 7.6122977 | AU26: 9.08 | AV26: 12.04 | AW26: 18.13 | AX26: 19.97 | AY26: 27.09 | AZ26: 33.64 | BA26: 39.67 | BB26: 45 | BC26: 46.23 | BD26: 47.979993 | BE26: 51.899988 | BF26: 53.0615 | BG26: 55.490377 | BH26: 56.656252 | BI26: 59.825548 | BJ26: 63.410101 | BK26: 64.782011 | BL26: 67.946981 | BM26: 70.162484 | BN26: 75.271446 | BO26: 79.126863 | BP26: 80.389565 | BQ26: 82.438955
A27: Bahrain | B27: BHR | C27: Individuals using the Internet (% of population) | D27: IT.NET.USER.ZS | AI27: 0 | AN27: 0.346 | AO27: 0.843 | AP27: 1.65 | AQ27: 3.22 | AR27: 4.72 | AS27: 6.1537325 | AT27: 15.038634 | AU27: 18.050721 | AV27: 21.554945 | AW27: 21.458681 | AX27: 21.303699 | AY27: 28.243999 | AZ27: 32.91 | BA27: 51.95 | BB27: 53 | BC27: 55 | BD27: 76.999967 | BE27: 88 | BF27: 90.00004 | BG27: 90.503133 | BH27: 93.478301 | BI27: 97.999981 | BJ27: 95.878136 | BK27: 98.644673 | BL27: 99.701504 | BM27: 99.671032 | BN27: 100 | BO27: 100 | BP27: 100 | BQ27: 100
A28: Bahamas, The | B28: BHS | C28: Individuals using the Internet (% of population) | D28: IT.NET.USER.ZS | AI28: 0 | AN28: 0.96 | AO28: 1.75 | AP28: 1.36 | AQ28: 2.34 | AR28: 3.76 | AS28: 8 | AT28: 11.8 | AU28: 18 | AV28: 20 | AW28: 22 | AX28: 25 | AY28: 26 | AZ28: 27 | BA28: 31.54 | BB28: 33.88 | BC28: 43 | BD28: 65 | BE28: 71.748199 | BF28: 72 | BG28: 76.919998 | BH28: 78 | BI28: 80 | BJ28: 80.599998 | BK28: 83 | BL28: 90.693298 | BM28: 92.443703 | BN28: 92.3498 | BO28: 92.255997 | BP28: 92.387299 | BQ28: 92.472702
A29: Bosnia and Herzegovina | B29: BIH | C29: Individuals using the Internet (% of population) | D29: IT.NET.USER.ZS | AI29: 0 | AO29: 0.0151 | AP29: 0.0594 | AQ29: 0.144 | AR29: 0.194 | AS29: 1.0829607 | AT29: 1.200527 | AU29: 2.6482679 | AV29: 3.9650368 | AW29: 15.468972 | AX29: 21.326701 | AY29: 25.122386 | AZ29: 27.92 | BA29: 34.66 | BB29: 37.74 | BC29: 42.75 | BD29: 43.887699 | BE29: 45.064499 | BF29: 48.521301 | BG29: 49.917702 | BH29: 52.599998 | BI29: 60.256535 | BJ29: 64.892021 | BK29: 70.120135 | BL29: 69.946348 | BM29: 73.211753 | BN29: 75.676201 | BO29: 78.845537 | BP29: 83.377154 | BQ29: 86.100911
A30: Belarus | B30: BLR | C30: Individuals using the Internet (% of population) | D30: IT.NET.USER.ZS | AI30: 0 | AM30: 0.000486 | AN30: 0.00292 | AO30: 0.0293 | AP30: 0.049 | AQ30: 0.0739 | AR30: 0.495 | AS30: 1.8603981 | AT30: 4.300616 | AU30: 8.9509713 | AY30: 16.2 | AZ30: 19.7 | BA30: 23 | BB30: 27.43 | BC30: 31.8 | BD30: 39.648896 | BE30: 46.91 | BF30: 54.17 | BG30: 59.016319 | BH30: 62.230361 | BI30: 71.113046 | BJ30: 74.436445 | BK30: 79.129887 | BL30: 82.789152 | BM30: 85.087912 | BN30: 86.888412 | BO30: 89.507331 | BP30: 91.5125 | BQ30: 94.261821
A31: Belize | B31: BLZ | C31: Individuals using the Internet (% of population) | D31: IT.NET.USER.ZS | AI31: 0 | AN31: 0.0454 | AO31: 0.883 | AP31: 1.29 | AQ31: 2.09 | AR31: 4.08 | AS31: 5.9638353 | AU31: 5.6842512 | AW31: 9.8 | AX31: 17 | AY31: 24 | AZ31: 24.6 | BA31: 26.299999 | BB31: 27.200001 | BC31: 28.2 | BD31: 30.700001 | BE31: 31 | BF31: 33.599998 | BG31: 38.700001 | BH31: 41.59 | BI31: 44.575699 | BJ31: 48.877102 | BK31: 53.593601 | BL31: 58.765202 | BM31: 64.435898 | BN31: 70.653702 | BO31: 69.983299 | BP31: 70.187202 | BQ31: 80.005823
A32: Bermuda | B32: BMU | C32: Individuals using the Internet (% of population) | D32: IT.NET.USER.ZS | AI32: 0 | AN32: 6.84 | AO32: 16.2 | AP32: 24.2 | AQ32: 32.1 | AR32: 39.9 | AS32: 42.94986 | AT32: 47.5097 | AU32: 52.031597 | AV32: 56.522012 | AW32: 60.990867 | AX32: 65.447066 | AY32: 69.899655 | AZ32: 74.350594 | BA32: 82.3 | BB32: 83.25 | BC32: 84.21 | BD32: 88.336 | BE32: 91.299305 | BF32: 95.3 | BG32: 96.8 | BH32: 98.32361 | BI32: 98 | BJ32: 98.37
A33: Bolivia | B33: BOL | C33: Individuals using the Internet (% of population) | D33: IT.NET.USER.ZS | AI33: 0 | AN33: 0.0668 | AO33: 0.196 | AP33: 0.448 | AQ33: 0.626 | AR33: 0.982 | AS33: 1.4427636 | AT33: 2.1204625 | AU33: 3.1171929 | AV33: 3.5085964 | AW33: 4.4399246 | AX33: 5.227584 | AY33: 6.2006713 | AZ33: 10.4992 | BA33: 12.5 | BB33: 16.799999 | BC33: 22.4 | BD33: 30 | BE33: 35.34 | BF33: 36.99 | BG33: 34.60162 | BH33: 37.486818 | BI33: 39.697498 | BJ33: 43.832298 | BK33: 44.286142 | BL33: 47.474819 | BM33: 59.940102 | BN33: 65.977379 | BO33: 72.622704 | BP33: 77.3004 | BQ33: 79.704697
A34: Brazil | B34: BRA | C34: Individuals using the Internet (% of population) | D34: IT.NET.USER.ZS | AI34: 0 | AJ34: 0.00329 | AK34: 0.0129 | AL34: 0.0255 | AM34: 0.0377 | AN34: 0.105 | AO34: 0.451 | AP34: 0.786 | AQ34: 1.48 | AR34: 2.04 | AS34: 2.8706852 | AT34: 4.5284949 | AU34: 9.1494251 | AV34: 13.207586 | AW34: 19.073672 | AX34: 21.022747 | AY34: 28.1784 | AZ34: 30.879999 | BA34: 33.83 | BB34: 39.22 | BC34: 40.65 | BD34: 45.69 | BE34: 48.56 | BF34: 51.04 | BG34: 54.551002 | BH34: 58.327952 | BI34: 60.87254 | BJ34: 67.471285 | BK34: 70.434283 | BL34: 73.91244 | BM34: 81.342694 | BN34: 80.689893 | BO34: 80.527751 | BP34: 84.150602 | BQ34: 84.463472
A35: Barbados | B35: BRB | C35: Individuals using the Internet (% of population) | D35: IT.NET.USER.ZS | AI35: 0 | AN35: 0.00775 | AO35: 0.389 | AP35: 0.783 | AQ35: 1.97 | AR35: 2.38 | AS35: 3.9736784 | AT35: 11.93645 | AU35: 27.836322 | AV35: 39.689627 | AW35: 49.8 | AX35: 52.5 | AY35: 55.299999 | AZ35: 58.200001 | BA35: 61.400002 | BB35: 64.699997 | BC35: 65.099998 | BD35: 66.5 | BE35: 71.199997 | BF35: 71.800003 | BG35: 71.924599 | BH35: 72.0494 | BI35: 71.572998 | BJ35: 71.148499 | BK35: 70.726501 | BL35: 70.307098 | BM35: 69.890099 | BN35: 69.475601 | BO35: 69.063599 | BP35: 69.675102 | BQ35: 70.3647
A36: Brunei Darussalam | B36: BRN | C36: Individuals using the Internet (% of population) | D36: IT.NET.USER.ZS | AI36: 0 | AN36: 1.02 | AO36: 3.3 | AP36: 4.83 | AQ36: 6.28 | AR36: 7.67 | AS36: 8.9962845 | AT36: 12.917769 | AU36: 15.32988 | AV36: 19.595003 | AW36: 29.715604 | AX36: 36.466392 | AY36: 42.186349 | AZ36: 44.68 | BA36: 46 | BB36: 49 | BC36: 53 | BD36: 56 | BE36: 60.273102 | BF36: 64.5 | BG36: 68.769997 | BH36: 71.199997 | BI36: 90 | BJ36: 94.866699 | BK36: 95 | BL36: 95 | BM36: 96.305496 | BN36: 97.628799 | BO36: 98.970426 | BP36: 98.970398 | BQ36: 96.298288
A37: Bhutan | B37: BTN | C37: Individuals using the Internet (% of population) | D37: IT.NET.USER.ZS | AI37: 0 | AR37: 0.138 | AS37: 0.40094445 | AT37: 0.86462856 | AU37: 1.6758026 | AV37: 2.4369124 | AW37: 3.1569842 | AX37: 3.8471 | AY37: 4.5183001 | AZ37: 5.92 | BA37: 6.55 | BB37: 7.17 | BC37: 13.6 | BD37: 14.4 | BE37: 15.6 | BF37: 22.4 | BG37: 30.299999 | BH37: 39.799999 | BI37: 46.503201 | BJ37: 54.335499 | BK37: 63.486801 | BL37: 74.179398 | BM37: 76.8508 | BN37: 85.636884 | BO37: 88.356201 | BP37: 90.0214 | BQ37: 91.277397
A38: Botswana | B38: BWA | C38: Individuals using the Internet (% of population) | D38: IT.NET.USER.ZS | AI38: 0 | AJ38: 0 | AN38: 0.0645 | AO38: 0.157 | AP38: 0.308 | AQ38: 0.602 | AR38: 1.12 | AS38: 2.9026666 | AT38: 3.4308868 | AU38: 3.3859224 | AV38: 3.3451902 | AW38: 3.3048893 | AX38: 3.2625999 | AY38: 4.289933 | AZ38: 5.28 | BA38: 6.25 | BB38: 6.1500001 | BC38: 6 | BD38: 9 | BE38: 16 | BF38: 30 | BG38: 36.744747 | BH38: 38.893799 | BI38: 41.168598 | BJ38: 43.576401 | BK38: 46.125099 | BL38: 48.8228 | BM38: 51.6782 | BN38: 54.700699 | BO38: 57.9 | BQ38: 57.4595
A39: Central African Republic | B39: CAF | C39: Individuals using the Internet (% of population) | D39: IT.NET.USER.ZS | AI39: 0 | AO39: 0.00585 | AP39: 0.0143 | AQ39: 0.0279 | AR39: 0.0409 | AS39: 0.053394174 | AT39: 0.078543428 | AU39: 0.12853712 | AV39: 0.15156334 | AW39: 0.2234014 | AX39: 0.26820001 | AY39: 0.31119999 | AZ39: 0.37581596 | BA39: 1 | BB39: 1.8 | BC39: 2 | BD39: 2.2 | BE39: 2.4000001 | BF39: 2.5 | BG39: 2.7 | BH39: 2.9000001 | BI39: 3.0999999 | BJ39: 4 | BK39: 5.0999999 | BL39: 7.5092001 | BO39: 13.7536 | BP39: 13.8417 | BQ39: 13.7825
A40: Canada | B40: CAN | C40: Individuals using the Internet (% of population) | D40: IT.NET.USER.ZS | AI40: 0.361 | AJ40: 0.57 | AK40: 0.916 | AL40: 1.18 | AM40: 2.38 | AN40: 4.16 | AO40: 6.76 | AP40: 15.1 | AQ40: 24.9 | AR40: 36.2 | AS40: 51.3 | AT40: 60.2 | AU40: 61.593299 | AV40: 64.2 | AW40: 65.955963 | AX40: 71.66 | AY40: 72.400002 | AZ40: 73.2 | BA40: 76.699997 | BB40: 80.3 | BC40: 80.3 | BD40: 83 | BE40: 83 | BF40: 85.800003 | BG40: 87.120003 | BH40: 90 | BI40: 91.160004 | BJ40: 92.701401 | BK40: 94.64 | BL40: 91.912903 | BM40: 92.3 | BN40: 93.937103 | BO40: 94 | BP40: 94.145302 | BQ40: 94.353302
A41: Central Europe and the Baltics | B41: CEB | C41: Individuals using the Internet (% of population) | D41: IT.NET.USER.ZS
A42: Switzerland | B42: CHE | C42: Individuals using the Internet (% of population) | D42: IT.NET.USER.ZS | AI42: 0.596 | AJ42: 1.18 | AK42: 1.75 | AL42: 2.17 | AM42: 2.72 | AN42: 3.55 | AO42: 4.55 | AP42: 15.1 | AQ42: 24.8 | AR42: 34 | AS42: 47.1 | AT42: 55.1 | AU42: 61.4 | AV42: 65.1 | AW42: 67.8 | AX42: 70.1 | AY42: 75.7 | AZ42: 77.2 | BA42: 79.2 | BB42: 81.3 | BC42: 83.9 | BD42: 85.193028 | BE42: 85.2 | BF42: 86.34 | BG42: 83.617251 | BH42: 87.479056 | BI42: 89.134688 | BJ42: 89.686148 | BK42: 91.800003 | BL42: 93.146087 | BM42: 94.349998 | BN42: 95.569372 | BO42: 96.452797 | BP42: 97.344366 | BQ42: 97.344398 | BR42: 97.321039
A43: Channel Islands | B43: CHI | C43: Individuals using the Internet (% of population) | D43: IT.NET.USER.ZS
A44: Chile | B44: CHL | C44: Individuals using the Internet (% of population) | D44: IT.NET.USER.ZS | AI44: 0 | AK44: 0.0365 | AL44: 0.0718 | AM44: 0.141 | AN44: 0.347 | AO44: 0.683 | AP44: 1.06 | AQ44: 1.66 | AR44: 4.1 | AS44: 16.6 | AT44: 19.1 | AU44: 22.1 | AV44: 25.473779 | AW44: 28.17791 | AX44: 31.175301 | AY44: 34.497751 | AZ44: 35.900002 | BA44: 37.299999 | BB44: 41.56 | BC44: 45 | BD44: 52.249607 | BE44: 55.049999 | BF44: 58 | BG44: 61.110001 | BH44: 76.629592 | BI44: 83.558586 | BJ44: 82.327487 | BK44: 84.900002 | BL44: 85.017601 | BM44: 87.459297 | BN44: 90.232803 | BO44: 92.318199 | BP44: 94.457423 | BQ44: 95.590243
A45: China | B45: CHN | C45: Individuals using the Internet (% of population) | D45: IT.NET.USER.ZS | AI45: 0 | AL45: 0.000169 | AM45: 0.00117 | AN45: 0.00495 | AO45: 0.0131 | AP45: 0.0324 | AQ45: 0.169 | AR45: 0.708 | AS45: 1.7759132 | AT45: 2.6396502 | AU45: 4.5957043 | AV45: 6.2 | AW45: 7.3 | AX45: 8.523257 | AY45: 10.523153 | AZ45: 16 | BA45: 22.6 | BB45: 28.9 | BC45: 34.3 | BD45: 38.3 | BE45: 42.300098 | BF45: 45.799999 | BG45: 47.900002 | BH45: 50.299999 | BI45: 53.2 | BJ45: 54.3 | BK45: 65.358398 | BL45: 64.080881 | BM45: 70.05276 | BN45: 73.053235 | BO45: 75.611316 | BP45: 90.6 | BQ45: 92 | BR45: 91.6
A46: Cote d'Ivoire | B46: CIV | C46: Individuals using the Internet (% of population) | D46: IT.NET.USER.ZS | AI46: 0 | AN46: 0.0002 | AO46: 0.00841 | AP46: 0.0188 | AQ46: 0.061 | AR46: 0.119 | AS46: 0.23146167 | AT46: 0.3957477 | AU46: 0.49792936 | AV46: 0.75866963 | AW46: 0.84928241 | AX46: 1.0391999 | AY46: 1.5249 | AZ46: 1.8 | BA46: 1.9 | BB46: 2 | BC46: 2.7 | BD46: 2.9000001 | BE46: 4.4000001 | BF46: 6.5999999 | BG46: 10 | BH46: 38.44 | BI46: 41.207815 | BJ46: 43.839921 | BK46: 37.546536 | BL46: 36.288955 | BM46: 36.016602 | BN46: 35.950699 | BO46: 38.413281 | BP46: 40.65285 | BQ46: 41.432199
A47: Cameroon | B47: CMR | C47: Individuals using the Internet (% of population) | D47: IT.NET.USER.ZS | AI47: 0 | AP47: 0.00677 | AQ47: 0.0132 | AR47: 0.129 | AS47: 0.25212008 | AT47: 0.27705132 | AU47: 0.36087158 | AV47: 0.58762261 | AW47: 0.97607542 | AX47: 1.4026999 | AY47: 2.0287001 | AZ47: 2.93 | BA47: 3.4000001 | BB47: 3.84 | BC47: 4.3000002 | BD47: 5 | BE47: 7.5 | BF47: 10 | BG47: 16.214872 | BH47: 18.299999 | BI47: 20.6 | BJ47: 23.202972 | BK47: 29.700001 | BL47: 36.5392 | BM47: 37.697498 | BN47: 38.892601 | BO47: 40.125599 | BP47: 42.243801 | BQ47: 46.258801
A48: Congo, Dem. Rep. | B48: COD | C48: Individuals using the Internet (% of population) | D48: IT.NET.USER.ZS | AI48: 0 | AO48: 0.000108 | AP48: 0.000211 | AQ48: 0.000413 | AR48: 0.00101 | AS48: 0.0059021137 | AT48: 0.011475782 | AU48: 0.092790702 | AV48: 0.13491484 | AW48: 0.19620838 | AX48: 0.238 | AY48: 0.29609999 | AZ48: 0.37000001 | BA48: 0.44 | BB48: 0.56 | BC48: 0.72 | BD48: 1.2 | BE48: 1.6799999 | BF48: 2.2 | BG48: 3 | BH48: 3.8 | BI48: 10.1 | BK48: 11.7 | BL48: 13.0297 | BM48: 14.5105 | BN48: 16.159599 | BO48: 17.996201 | BP48: 18.967899 | BQ48: 19.6735
A49: Congo, Rep. | B49: COG | C49: Individuals using the Internet (% of population) | D49: IT.NET.USER.ZS | AI49: 0 | AO49: 0.00353 | AP49: 0.00347 | AQ49: 0.00342 | AR49: 0.0168 | AS49: 0.026354732 | AT49: 0.032223616 | AU49: 0.15724952 | AV49: 0.46001419 | AW49: 1.0775049 | AX49: 1.4634 | AY49: 2.0079999 | AZ49: 2.7597044 | BA49: 4.2875099 | BB49: 4.5 | BC49: 5 | BD49: 5.6 | BE49: 6.1066999 | BF49: 6.5999999 | BG49: 7.1100001 | BH49: 7.6160002 | BI49: 8.1218996 | BJ49: 8.6499996 | BK49: 11.8071 | BL49: 16.1164 | BM49: 21.998501 | BN49: 30.027399 | BO49: 40.986698 | BP49: 43.150398 | BQ49: 47.251598
A50: Colombia | B50: COL | C50: Individuals using the Internet (% of population) | D50: IT.NET.USER.ZS | AI50: 0 | AM50: 0.107 | AN50: 0.188 | AO50: 0.33 | AP50: 0.551 | AQ50: 1.13 | AR50: 1.7 | AS50: 2.207533 | AT50: 2.8542 | AU50: 4.6 | AV50: 7.3889237 | AW50: 9.1186903 | AX50: 11.007264 | AY50: 15.341675 | AZ50: 21.799999 | BA50: 25.6 | BB50: 30 | BC50: 36.5 | BD50: 40.350916 | BE50: 48.98 | BF50: 51.7 | BG50: 52.568137 | BH50: 55.904973 | BI50: 58.136494 | BJ50: 62.25988 | BK50: 64.126377 | BL50: 65.006901 | BM50: 69.795335 | BN50: 73.028374 | BO50: 72.796379 | BP50: 77.336863 | BQ50: 79.345433
A51: Comoros | B51: COM | C51: Individuals using the Internet (% of population) | D51: IT.NET.USER.ZS | AI51: 0 | AP51: 0 | AQ51: 0.0379 | AR51: 0.148 | AS51: 0.27174061 | AT51: 0.44306837 | AU51: 0.55486967 | AV51: 0.84818937 | AW51: 1.3273272 | AX51: 2 | AY51: 2.2 | AZ51: 2.5 | BA51: 3 | BB51: 3.5 | BC51: 5.0999999 | BD51: 5.5 | BE51: 5.9752998 | BF51: 6.5 | BG51: 6.98 | BH51: 7.4591999 | BI51: 7.9383001 | BJ51: 8.4782 | BL51: 16.383801 | BM51: 22.420401 | BN51: 30.6812 | BO51: 31.3741 | BP51: 31.9275 | BQ51: 32.517502
A52: Cabo Verde | B52: CPV | C52: Individuals using the Internet (% of population) | D52: IT.NET.USER.ZS | AI52: 0 | AP52: 0.241 | AQ52: 0.473 | AR52: 1.16 | AS52: 1.8224439 | AT52: 2.6853327 | AU52: 3.5187572 | AV52: 4.3248854 | AW52: 5.3188321 | AX52: 6.0740871 | AY52: 6.808911 | AZ52: 8.2832198 | BA52: 14 | BB52: 21 | BC52: 30 | BD52: 32 | BE52: 34.74 | BF52: 37.5 | BG52: 40.259998 | BH52: 42.683014 | BI52: 50.322818 | BJ52: 57.162146 | BK52: 59.5 | BL52: 61.943398 | BM52: 69.373398 | BN52: 70.282501 | BO52: 73.3274 | BP52: 74.599197 | BQ52: 74.735199
A53: Costa Rica | B53: CRI | C53: Individuals using the Internet (% of population) | D53: IT.NET.USER.ZS | AI53: 0 | AK53: 0.00111 | AL53: 0.0815 | AM53: 0.28 | AN53: 0.417 | AO53: 0.841 | AP53: 1.64 | AQ53: 2.67 | AR53: 3.9 | AS53: 5.800253 | AT53: 9.5594821 | AU53: 19.894851 | AV53: 20.333615 | AW53: 20.792307 | AX53: 22.07 | AY53: 25.1 | AZ53: 28.4 | BA53: 32.29 | BB53: 34.33 | BC53: 36.5 | BD53: 39.212196 | BE53: 47.5 | BF53: 45.96 | BG53: 53 | BH53: 59.76295 | BI53: 65.880449 | BJ53: 71.581665 | BK53: 73.479728 | BL53: 81.202596 | BM53: 80.530186 | BN53: 82.749016 | BO53: 82.598011 | BP53: 85.395148 | BQ53: 87.170197
A54: Caribbean small states | B54: CSS | C54: Individuals using the Internet (% of population) | D54: IT.NET.USER.ZS
A55: Cuba | B55: CUB | C55: Individuals using the Internet (% of population) | D55: IT.NET.USER.ZS | AI55: 0 | AN55: 9.17e-05 | AO55: 0.0319 | AP55: 0.0682 | AQ55: 0.227 | AR55: 0.315 | AS55: 0.54118255 | AT55: 1.0797517 | AU55: 3.770585 | AV55: 5.2412691 | AW55: 8.4079848 | AX55: 9.7380622 | AY55: 11.159601 | AZ55: 11.69 | BA55: 12.94 | BB55: 14.33 | BC55: 15.9 | BD55: 16.017291 | BE55: 21.200001 | BF55: 27.93 | BG55: 29.070184 | BH55: 37.305097 | BI55: 42.978675 | BJ55: 57.148404 | BK55: 62.678924 | BL55: 67.970809 | BM55: 71.119075 | BN55: 67.643549 | BO55: 67.884102 | BP55: 69.555801 | BQ55: 70.476997
A56: Curacao | B56: CUW | C56: Individuals using the Internet (% of population) | D56: IT.NET.USER.ZS | BI56: 61.855511 | BJ56: 68.127216
A57: Cayman Islands | B57: CYM | C57: Individuals using the Internet (% of population) | D57: IT.NET.USER.ZS | AI57: 0 | AL57: 0 | AM57: 0 | AN57: 3.95 | AX57: 38.034383 | AY57: 44.5 | AZ57: 52 | BA57: 61 | BB57: 64.5 | BC57: 66 | BD57: 69.465945 | BE57: 69.7 | BF57: 71.4 | BG57: 74.1 | BH57: 77 | BI57: 79 | BJ57: 81.067693
A58: Cyprus | B58: CYP | C58: Individuals using the Internet (% of population) | D58: IT.NET.USER.ZS | AI58: 0 | AK58: 0.0501 | AL58: 0.0564 | AM58: 0.111 | AN58: 0.41 | AO58: 0.673 | AP58: 4.38 | AQ58: 8.89 | AR58: 11.3 | AS58: 15.255394 | AT58: 18.818759 | AU58: 28.32 | AV58: 30.09 | AW58: 33.83 | AX58: 32.81 | AY58: 35.83 | AZ58: 40.77 | BA58: 42.31 | BB58: 49.81 | BC58: 52.99 | BD58: 56.859892 | BE58: 60.689868 | BF58: 65.4548 | BG58: 69.328697 | BH58: 71.715741 | BI58: 75.900205 | BJ58: 80.743189 | BK58: 84.433583 | BL58: 86.06363 | BM58: 90.801946 | BN58: 90.759516 | BO58: 89.600992 | BP58: 91.221104 | BQ58: 89.600992
A59: Czechia | B59: CZE | C59: Individuals using the Internet (% of population) | D59: IT.NET.USER.ZS | AI59: 0 | AL59: 0.581 | AM59: 1.26 | AN59: 1.45 | AO59: 1.94 | AP59: 2.92 | AQ59: 3.9 | AR59: 6.83 | AS59: 9.7805279 | AT59: 14.697172 | AU59: 23.93 | AV59: 34.3 | AW59: 35.5 | AX59: 35.27 | AY59: 47.93 | AZ59: 51.93 | BA59: 62.97 | BB59: 64.43 | BC59: 68.82 | BD59: 70.49 | BE59: 73.430008 | BF59: 74.1104 | BG59: 74.231712 | BH59: 75.668839 | BI59: 76.481199 | BJ59: 78.719173 | BK59: 80.688168 | BL59: 80.866944 | BM59: 81.338897 | BN59: 82.670624 | BO59: 84.540094 | BP59: 85.994048 | BQ59: 87.68776
A60: Germany | B60: DEU | C60: Individuals using the Internet (% of population) | D60: IT.NET.USER.ZS | AI60: 0.126 | AJ60: 0.25 | AK60: 0.435 | AL60: 0.464 | AM60: 0.923 | AN60: 1.84 | AO60: 3.05 | AP60: 6.71 | AQ60: 9.88 | AR60: 20.8 | AS60: 30.216347 | AT60: 31.650939 | AU60: 48.82 | AV60: 55.9 | AW60: 64.73 | AX60: 68.71 | AY60: 72.16 | AZ60: 75.16 | BA60: 78 | BB60: 79 | BC60: 82 | BD60: 81.27 | BE60: 82.349998 | BF60: 84.17 | BG60: 86.193701 | BH60: 87.589799 | BI60: 84.165207 | BJ60: 84.394154 | BK60: 87.037112 | BL60: 88.134517 | BM60: 89.812941 | BN60: 91.43061 | BO60: 91.629844 | BP60: 92.476376 | BQ60: 93.499996
A61: Djibouti | B61: DJI | C61: Individuals using the Internet (% of population) | D61: IT.NET.USER.ZS | AI61: 0 | AN61: 0.016 | AO61: 0.0312 | AP61: 0.0829 | AQ61: 0.0947 | AR61: 0.106 | AS61: 0.19450053 | AT61: 0.34352626 | AU61: 0.4869717 | AV61: 0.62594023 | AW61: 0.78131718 | AX61: 0.95359999 | AY61: 1.27 | AZ61: 1.62 | BA61: 2.26 | BB61: 4 | BC61: 6.5 | BD61: 7 | BE61: 9.3999996 | BF61: 12.7 | BG61: 17 | BH61: 22.9 | BI61: 30.799999 | BJ61: 55.681409 | BK61: 57.061699 | BL61: 58.4762 | BM61: 59.925701 | BN61: 61.411201 | BO61: 63.776001 | BP61: 64.758698 | BQ61: 65.298897
A62: Dominica | B62: DMA | C62: Individuals using the Internet (% of population) | D62: IT.NET.USER.ZS | AI62: 0 | AN62: 0.549 | AO62: 1.17 | AQ62: 2.93 | AR62: 2.93 | AS62: 8.8148442 | AT62: 13.245228 | AU62: 18.424893 | AV62: 23.62042 | AW62: 30.319613 | AX62: 38.543598 | AY62: 39.398201 | AZ62: 40.274502 | BA62: 41.16 | BB62: 42.02 | BC62: 47.45 | BD62: 48.599998 | BE62: 49.799999 | BF62: 51 | BG62: 57.5 | BH62: 65 | BI62: 67.029999 | BJ62: 69.619698 | BL62: 73.382004 | BM62: 75.6567 | BN62: 78.079498 | BO62: 80.579803 | BP62: 81.336502 | BQ62: 82.046898
A63: Denmark | B63: DNK | C63: Individuals using the Internet (% of population) | D63: IT.NET.USER.ZS | AI63: 0.0973 | AJ63: 0.194 | AK63: 0.387 | AL63: 0.578 | AM63: 1.34 | AN63: 3.83 | AO63: 5.71 | AP63: 11.4 | AQ63: 22.7 | AR63: 30.6 | AS63: 39.172431 | AT63: 42.957525 | AU63: 64.25 | AV63: 76.26 | AW63: 80.93 | AX63: 82.74 | AY63: 86.65 | AZ63: 85.03 | BA63: 85.02 | BB63: 86.84 | BC63: 88.72 | BD63: 89.810013 | BE63: 92.260012 | BF63: 94.6297 | BG63: 95.993505 | BH63: 96.330502 | BI63: 96.967785 | BJ63: 97.099362 | BK63: 97.319204 | BL63: 98.046435 | BM63: 96.549146 | BN63: 98.865851 | BO63: 97.860118 | BP63: 98.775592 | BQ63: 99.769152
A64: Dominican Republic | B64: DOM | C64: Individuals using the Internet (% of population) | D64: IT.NET.USER.ZS | AI64: 0 | AN64: 0.0172 | AO64: 0.075 | AP64: 0.143 | AQ64: 0.234 | AR64: 1.1 | AS64: 3.7046924 | AT64: 4.4293907 | AU64: 6.8237257 | AV64: 7.8983929 | AW64: 8.8655535 | AX64: 11.483198 | AY64: 14.844928 | AZ64: 17.66 | BA64: 20.82 | BB64: 27.72 | BC64: 31.4 | BD64: 38 | BE64: 42.32 | BF64: 45.9 | BG64: 49.580002 | BH64: 54.215766 | BI64: 63.870865 | BJ64: 67.571245 | BK64: 74.822048 | BL64: 79.7155 | BM64: 81.617302 | BN64: 85.242986 | BO64: 81.512697 | BP64: 86.1269 | BQ64: 91.002245
A65: Algeria | B65: DZA | C65: Individuals using the Internet (% of population) | D65: IT.NET.USER.ZS | AI65: 0 | AM65: 0.000361 | AN65: 0.00177 | AO65: 0.00174 | AP65: 0.0103 | AQ65: 0.0202 | AR65: 0.2 | AS65: 0.49170568 | AT65: 0.64611402 | AU65: 1.5916413 | AV65: 2.1953597 | AW65: 4.6344751 | AX65: 5.8439002 | AY65: 7.375985 | AZ65: 9.4511906 | BA65: 10.18 | BB65: 11.23 | BC65: 12.5 | BD65: 14.9 | BE65: 18.200001 | BF65: 22.5 | BG65: 29.5 | BH65: 38.200001 | BI65: 42.945499 | BJ65: 47.691101 | BK65: 49.038468 | BL65: 55.790699 | BM65: 63.472698 | BN65: 72.212402 | BO65: 74.781502 | BP65: 76.197601 | BQ65: 77.417801
A66: East Asia & Pacific (excluding high income) | B66: EAP | C66: Individuals using the Internet (% of population) | D66: IT.NET.USER.ZS | AX66: 8.3 | AY66: 10.1 | AZ66: 14.3 | BA66: 19.2 | BB66: 23.7 | BC66: 28.9 | BD66: 32.3 | BE66: 35.7 | BF66: 38.2 | BG66: 40.6 | BH66: 43.5 | BI66: 49.6 | BJ66: 53.9 | BK66: 59.1 | BL66: 64 | BM66: 72.2 | BN66: 77.6 | BO66: 81.6 | BP66: 84.2 | BQ66: 86.1 | BR66: 88.1
A67: Early-demographic dividend | B67: EAR | C67: Individuals using the Internet (% of population) | D67: IT.NET.USER.ZS
A68: East Asia & Pacific | B68: EAS | C68: Individuals using the Internet (% of population) | D68: IT.NET.USER.ZS | AX68: 14.7 | AY68: 16.6 | AZ68: 20.8 | BA68: 25.2 | BB68: 29.5 | BC68: 34.2 | BD68: 37.3 | BE68: 40.4 | BF68: 43.2 | BG68: 45.5 | BH68: 48.3 | BI68: 53.9 | BJ68: 57.8 | BK68: 62.5 | BL68: 67.1 | BM68: 73.9 | BN68: 78.8 | BO68: 82.4 | BP68: 84.9 | BQ68: 86.6 | BR68: 88.4
A69: Europe & Central Asia (excluding high income) | B69: ECA | C69: Individuals using the Internet (% of population) | D69: IT.NET.USER.ZS | AX69: 8.9 | AY69: 11.6 | AZ69: 16.3 | BA69: 20.6 | BB69: 25 | BC69: 30.1 | BD69: 34.9 | BE69: 39.4 | BF69: 43.2 | BG69: 48.6 | BH69: 51.9 | BI69: 56.2 | BJ69: 60.6 | BK69: 65.8 | BL69: 70.3 | BM69: 74.5 | BN69: 79.1 | BO69: 82 | BP69: 84.6 | BQ69: 85.8 | BR69: 87.5
A70: Europe & Central Asia | B70: ECS | C70: Individuals using the Internet (% of population) | D70: IT.NET.USER.ZS | AX70: 34.7 | AY70: 38 | AZ70: 43.6 | BA70: 48.1 | BB70: 52.7 | BC70: 57 | BD70: 60.2 | BE70: 63.8 | BF70: 66.1 | BG70: 68.9 | BH70: 69.9 | BI70: 72.3 | BJ70: 74.5 | BK70: 78.1 | BL70: 80.3 | BM70: 83.4 | BN70: 86.3 | BO70: 87.9 | BP70: 89.6 | BQ70: 90.9 | BR70: 92.4
A71: Ecuador | B71: ECU | C71: Individuals using the Internet (% of population) | D71: IT.NET.USER.ZS | AI71: 0 | AK71: 0.00512 | AL71: 0.0164 | AM71: 0.0348 | AN71: 0.0438 | AO71: 0.0862 | AP71: 0.11 | AQ71: 0.125 | AR71: 0.823 | AS71: 1.4621885 | AT71: 2.6704437 | AU71: 4.2607969 | AV71: 4.4602283 | AW71: 4.8344426 | AX71: 5.9942999 | AY71: 7.1999998 | AZ71: 10.8 | BA71: 18.8 | BB71: 24.6 | BC71: 29.03 | BD71: 31.366808 | BE71: 35.135146 | BF71: 40.279122 | BG71: 45.590391 | BH71: 48.940434 | BI71: 54.062925 | BJ71: 55.799999 | BK71: 57.5 | BL71: 59.2 | BM71: 70.7 | BN71: 69.1148 | BO71: 69.718114 | BP71: 72.694315 | BQ71: 77.172731
A72: Egypt, Arab Rep. | B72: EGY | C72: Individuals using the Internet (% of population) | D72: IT.NET.USER.ZS | AI72: 0 | AL72: 0.000976 | AM72: 0.00638 | AN72: 0.0313 | AO72: 0.0615 | AP72: 0.0905 | AQ72: 0.148 | AR72: 0.29 | AS72: 0.64126504 | AT72: 0.83894561 | AU72: 2.7199997 | AV72: 4.0378851 | AW72: 11.92 | AX72: 12.75 | AY72: 13.66 | AZ72: 16.03 | BA72: 18.01 | BB72: 20 | BC72: 21.6 | BD72: 25.6 | BE72: 26.4 | BF72: 29.4 | BG72: 33.894604 | BH72: 37.819383 | BI72: 41.248067 | BJ72: 44.950204 | BK72: 46.924337 | BL72: 57.282866 | BM72: 71.914201 | BN72: 72.056 | BO72: 72.198066 | BP72: 74.011902 | BQ72: 74.648399
A73: Euro area | B73: EMU | C73: Individuals using the Internet (% of population) | D73: IT.NET.USER.ZS
A74: Eritrea | B74: ERI | C74: Individuals using the Internet (% of population) | D74: IT.NET.USER.ZS | AI74: 0 | AL74: 0 | AM74: 0 | AN74: 0 | AO74: 0 | AP74: 0.00902 | AQ74: 0.00877 | AR74: 0.0255 | AS74: 0.13671194 | AT74: 0.15781529 | AU74: 0.22709014 | AZ74: 0.41 | BA74: 0.47 | BB74: 0.54000002 | BC74: 0.61000001 | BD74: 0.69999999 | BE74: 0.80000001 | BF74: 0.89999998 | BG74: 0.99000001 | BH74: 1.0836999 | BI74: 1.1770999 | BJ74: 2.4960999 | BK74: 5.2930002 | BL74: 11.2238 | BM74: 14.3494
A75: Spain | B75: ESP | C75: Individuals using the Internet (% of population) | D75: IT.NET.USER.ZS | AI75: 0.0129 | AJ75: 0.0257 | AK75: 0.0768 | AL75: 0.128 | AM75: 0.28 | AN75: 0.381 | AO75: 1.33 | AP75: 2.8 | AQ75: 4.36 | AR75: 7.09 | AS75: 13.624961 | AT75: 18.148723 | AU75: 20.39 | AV75: 39.93 | AW75: 44.01 | AX75: 47.88 | AY75: 50.37 | AZ75: 55.11 | BA75: 59.6 | BB75: 62.4 | BC75: 65.8 | BD75: 67.089999 | BE75: 69.81 | BF75: 71.635 | BG75: 76.186709 | BH75: 78.689632 | BI75: 80.561333 | BJ75: 84.602246 | BK75: 86.107236 | BL75: 90.718665 | BM75: 93.205649 | BN75: 93.897522 | BO75: 94.485543 | BP75: 95.445645 | BQ75: 95.757452
A76: Estonia | B76: EST | C76: Individuals using the Internet (% of population) | D76: IT.NET.USER.ZS | AI76: 0 | AK76: 0.0655 | AL76: 0.301 | AM76: 1.16 | AN76: 2.78 | AO76: 3.53 | AP76: 5.71 | AQ76: 10.8 | AR76: 14.5 | AS76: 28.576954 | AT76: 31.52749 | AU76: 41.52 | AV76: 45.32 | AW76: 53.2 | AX76: 61.45 | AY76: 63.51 | AZ76: 66.19 | BA76: 70.58 | BB76: 72.5 | BC76: 74.1 | BD76: 76.5 | BE76: 78.389926 | BF76: 80.0043 | BG76: 84.241528 | BH76: 88.409704 | BI76: 87.240233 | BJ76: 88.102457 | BK76: 89.357008 | BL76: 90.228928 | BM76: 89.058287 | BN76: 90.979702 | BO76: 91.520165 | BP76: 93.183422 | BQ76: 92.237962
A77: Ethiopia | B77: ETH | C77: Individuals using the Internet (% of population) | D77: IT.NET.USER.ZS | AI77: 0 | AN77: 1.75e-05 | AO77: 0.0017 | AP77: 0.00497 | AQ77: 0.00966 | AR77: 0.0125 | AS77: 0.015263767 | AT77: 0.037162381 | AU77: 0.072402262 | AV77: 0.10581166 | AW77: 0.15533452 | AX77: 0.21965982 | AY77: 0.31059266 | AZ77: 0.37 | BA77: 0.44999999 | BB77: 0.54000002 | BC77: 0.75 | BD77: 1.1 | BE77: 2.9000001 | BF77: 4.5999999 | BG77: 7.6999998 | BH77: 13.855176 | BI77: 15.366924 | BJ77: 15.6244 | BK77: 15.8862 | BL77: 15.9846 | BM77: 16.069599 | BN77: 16.698103 | BO77: 17.9837 | BP77: 20.3375 | BQ77: 21.941299
A78: European Union | B78: EUU | C78: Individuals using the Internet (% of population) | D78: IT.NET.USER.ZS
A79: Fragility, Conflict, and Violence (FCV) situations | B79: FCV | C79: Individuals using the Internet (% of population) | D79: IT.NET.USER.ZS
A80: Finland | B80: FIN | C80: Individuals using the Internet (% of population) | D80: IT.NET.USER.ZS | AI80: 0.401 | AJ80: 1.4 | AK80: 1.89 | AL80: 2.57 | AM80: 4.92 | AN80: 13.9 | AO80: 16.8 | AP80: 19.5 | AQ80: 25.5 | AR80: 32.3 | AS80: 37.248462 | AT80: 43.105363 | AU80: 62.43 | AV80: 69.22 | AW80: 72.39 | AX80: 74.48 | AY80: 79.66 | AZ80: 80.78 | BA80: 83.67 | BB80: 82.49 | BC80: 86.89 | BD80: 88.709995 | BE80: 89.879998 | BF80: 91.5144 | BG80: 86.530393 | BH80: 86.422133 | BI80: 87.70365 | BJ80: 87.468929 | BK80: 88.88996 | BL80: 89.607385 | BM80: 92.170271 | BN80: 92.808061 | BO80: 92.988795 | BP80: 93.513851 | BQ80: 93.724052
A81: Fiji | B81: FJI | C81: Individuals using the Internet (% of population) | D81: IT.NET.USER.ZS | AI81: 0 | AL81: 0.00668 | AM81: 0.00791 | AN81: 0.00912 | AO81: 0.0644 | AP81: 0.223 | AQ81: 0.633 | AR81: 0.942 | AS81: 1.4968547 | AT81: 1.8579786 | AU81: 6.1526497 | AV81: 6.7254347 | AW81: 7.4129435 | AX81: 8.4536366 | AY81: 9.6000384 | AZ81: 10.8978 | BA81: 13 | BB81: 17 | BC81: 20 | BD81: 28 | BE81: 33.742401 | BF81: 35.200001 | BG81: 37.400002 | BH81: 42.5 | BI81: 49.419998 | BJ81: 53.6474 | BK81: 58.236401 | BL81: 63.217899 | BM81: 68.625603 | BN81: 70.568001 | BO81: 72.565498 | BP81: 74.116096 | BQ81: 74.7052
A82: France | B82: FRA | C82: Individuals using the Internet (% of population) | D82: IT.NET.USER.ZS | AI82: 0.0528 | AJ82: 0.14 | AK82: 0.279 | AL82: 0.591 | AM82: 0.9 | AN82: 1.64 | AO82: 2.58 | AP82: 4.26 | AQ82: 6.32 | AR82: 9.13 | AS82: 14.307924 | AT82: 26.325904 | AU82: 30.18 | AV82: 36.14 | AW82: 39.15 | AX82: 42.87 | AY82: 46.87 | AZ82: 66.09 | BA82: 70.68 | BB82: 71.58 | BC82: 77.28 | BD82: 77.819999 | BE82: 81.44 | BF82: 81.9198 | BG82: 83.7511 | BH82: 78.006038 | BI82: 79.269811 | BJ82: 80.50246 | BK82: 82.043187 | BL82: 83.339744 | BM82: 84.706398 | BN82: 86.095486 | BO82: 85.333317 | BP82: 86.836358 | BQ82: 88.653816
A83: Faroe Islands | B83: FRO | C83: Individuals using the Internet (% of population) | D83: IT.NET.USER.ZS | AI83: 0 | AN83: 0 | AO83: 2.32 | AP83: 4.6 | AQ83: 11.3 | AR83: 22.3 | AS83: 32.916392 | AT83: 43.246984 | AU83: 53.299222 | AV83: 58.912641 | AW83: 66.533599 | AX83: 67.902632 | AY83: 69.359445 | AZ83: 75.98 | BA83: 75.57 | BB83: 75.18 | BC83: 75.2 | BD83: 80.732173 | BE83: 85.335189 | BF83: 90 | BG83: 93.3 | BH83: 94.2 | BI83: 95.108682 | BJ83: 97.581959
A84: Micronesia, Fed. Sts. | B84: FSM | C84: Individuals using the Internet (% of population) | D84: IT.NET.USER.ZS | AI84: 0 | AO84: 0.278 | AP84: 0.571 | AQ84: 1.86 | AR84: 2.8 | AS84: 3.7348621 | AT84: 4.6605272 | AU84: 5.5700997 | AV84: 9.2325021 | AW84: 11.017867 | AX84: 11.8814 | AY84: 12.7503 | AZ84: 13.6211 | BA84: 14.49 | BB84: 15.35 | BC84: 20 | BD84: 22.799999 | BE84: 25.9744 | BF84: 27.799999 | BG84: 29.65 | BH84: 31.501101 | BI84: 33.3522 | BJ84: 35.3041 | BK84: 36.614601 | BL84: 37.973701 | BM84: 39.383301 | BO84: 39.027901 | BP84: 39.398899 | BQ84: 39.523602
A85: Gabon | B85: GAB | C85: Individuals using the Internet (% of population) | D85: IT.NET.USER.ZS | AI85: 0 | AO85: 0 | AP85: 0.048 | AQ85: 0.17 | AR85: 0.249 | AS85: 1.2161406 | AT85: 1.3476202 | AU85: 1.9395301 | AV85: 2.6595866 | AW85: 2.9790698 | AX85: 4.8932647 | AY85: 5.4892008 | AZ85: 5.7670002 | BA85: 7.5 | BB85: 9.5 | BC85: 13 | BD85: 18 | BE85: 24 | BF85: 30.538 | BG85: 38.071201 | BH85: 45.7845 | BI85: 48.052299 | BJ85: 51.6049 | BK85: 55.4202 | BL85: 59.517601 | BM85: 63.9179 | BN85: 65.768097 | BO85: 67.6717 | BP85: 68.197899 | BQ85: 68.720901
A86: United Kingdom | B86: GBR | C86: Individuals using the Internet (% of population) | D86: IT.NET.USER.ZS | AI86: 0.0874 | AJ86: 0.174 | AK86: 0.261 | AL86: 0.52 | AM86: 1.04 | AN86: 1.9 | AO86: 4.12 | AP86: 7.39 | AQ86: 13.7 | AR86: 21.3 | AS86: 26.821754 | AT86: 33.481095 | AU86: 56.48 | AV86: 64.82 | AW86: 65.61 | AX86: 70 | AY86: 68.82 | AZ86: 75.09 | BA86: 78.39 | BB86: 83.56 | BC86: 85 | BD86: 85.379999 | BE86: 87.479998 | BF86: 89.8441 | BG86: 91.613301 | BH86: 92.0003 | BI86: 94.775801 | BJ86: 90.42455 | BK86: 90.692009 | BL86: 92.516629 | BM86: 94.818201 | BN86: 96.196503 | BO86: 95.465302 | BP86: 95.447197 | BQ86: 95.472099
A87: Georgia | B87: GEO | C87: Individuals using the Internet (% of population) | D87: IT.NET.USER.ZS | AI87: 0 | AN87: 0.0118 | AO87: 0.0401 | AP87: 0.0609 | AQ87: 0.103 | AR87: 0.416 | AS87: 0.4847463 | AT87: 0.99234444 | AU87: 1.5878756 | AV87: 2.5588165 | AW87: 3.8862214 | AX87: 6.0795002 | AY87: 7.5268768 | AZ87: 8.26 | BA87: 10.01 | BB87: 20.07 | BC87: 26.9 | BD87: 31.52 | BE87: 36.939999 | BF87: 43.3 | BG87: 49.102455 | BH87: 47.56976 | BI87: 58.45929 | BJ87: 59.705505 | BK87: 62.717908 | BL87: 68.846714 | BM87: 72.531575 | BN87: 76.442709 | BO87: 78.711275 | BP87: 81.884256 | BQ87: 83.798557
A88: Ghana | B88: GHA | C88: Individuals using the Internet (% of population) | D88: IT.NET.USER.ZS | AI88: 0 | AN88: 0.000348 | AO88: 0.00565 | AP88: 0.0275 | AQ88: 0.0322 | AR88: 0.105 | AS88: 0.1536153 | AT88: 0.20000806 | AU88: 0.83028403 | AV88: 1.1930579 | AW88: 1.7167977 | AX88: 1.8311975 | AY88: 2.723176 | AZ88: 3.85 | BA88: 4.27 | BB88: 5.44 | BC88: 7.8 | BD88: 9 | BE88: 10.6 | BF88: 15 | BG88: 19 | BH88: 23 | BI88: 28 | BJ88: 37.884201 | BK88: 43 | BL88: 22.0732 | BM88: 62.517601 | BN88: 68.6 | BO88: 69.9133 | BP88: 70.674301 | BQ88: 72.175697
A89: Gibraltar | B89: GIB | C89: Individuals using the Internet (% of population) | D89: IT.NET.USER.ZS | AI89: 0 | AP89: 2.66 | AQ89: 4.18 | AR89: 5.94 | AS89: 19.131638 | AT89: 21.171109 | AU89: 23.67024 | AV89: 28.32578 | AW89: 32.886083 | AX89: 39.070131 | AY89: 45.298648 | AZ89: 51.61 | BA89: 58 | BB89: 65.07 | BC89: 65 | BD89: 65 | BE89: 65.017 | BI89: 94.444472
A90: Guinea | B90: GIN | C90: Individuals using the Internet (% of population) | D90: IT.NET.USER.ZS | AI90: 0 | AM90: 0.000138 | AN90: 0.000669 | AO90: 0.00195 | AP90: 0.0038 | AQ90: 0.0062 | AR90: 0.0608 | AS90: 0.095424924 | AT90: 0.17554187 | AU90: 0.40202275 | AV90: 0.45096037 | AW90: 0.50881933 | AX90: 0.54229999 | AY90: 0.63749999 | AZ90: 0.78002528 | BA90: 0.92 | BB90: 0.94 | BC90: 1 | BD90: 2 | BE90: 3.0999999 | BF90: 4.5 | BG90: 6.4000001 | BH90: 9.1999998 | BI90: 13.1 | BJ90: 18.700001 | BK90: 21.830023 | BL90: 23.890499 | BM90: 26.1455 | BN90: 28.6133 | BO90: 31.313999 | BP90: 32.315601 | BQ90: 33.304699
A91: Gambia, The | B91: GMB | C91: Individuals using the Internet (% of population) | D91: IT.NET.USER.ZS | AI91: 0 | AN91: 0.00922 | AO91: 0.0355 | AP91: 0.0513 | AQ91: 0.206 | AR91: 0.716 | AS91: 0.92179492 | AT91: 1.3367912 | AU91: 1.7967799 | AV91: 2.4367812 | AW91: 3.3080035 | AX91: 3.799 | AY91: 5.2376912 | AZ91: 6.2050374 | BA91: 6.8800001 | BB91: 7.6300001 | BC91: 9.2 | BD91: 10.8703 | BE91: 12.4492 | BF91: 14 | BG91: 15.56 | BH91: 17.599501 | BI91: 19.906401 | BJ91: 22.5156 | BK91: 28.309 | BL91: 31.118299 | BM91: 36.011002 | BN91: 41.6731 | BO91: 48.225399 | BP91: 48.728298 | BQ91: 49.494301
A92: Guinea-Bissau | B92: GNB | C92: Individuals using the Internet (% of population) | D92: IT.NET.USER.ZS | AI92: 0 | AP92: 0.0164 | AQ92: 0.0241 | AR92: 0.118 | AS92: 0.23010317 | AT92: 0.29956914 | AU92: 1.0229932 | AV92: 1.3541975 | AW92: 1.8081422 | AX92: 1.9014 | AY92: 2.0572 | AZ92: 2.2063 | BA92: 2.3548887 | BB92: 2.3032806 | BC92: 2.45 | BD92: 2.6719999 | BE92: 2.8940001 | BF92: 3.0999999 | BG92: 3.3199999 | BH92: 6.0999999 | BI92: 13.8 | BJ92: 14.8 | BK92: 15.7 | BL92: 17.921499 | BM92: 20.4573 | BN92: 23.3519 | BO92: 27.6738 | BP92: 28.7124 | BQ92: 29.777399
A93: Equatorial Guinea | B93: GNQ | C93: Individuals using the Internet (% of population) | D93: IT.NET.USER.ZS | AI93: 0 | AP93: 0.0415 | AQ93: 0.0944 | AR93: 0.0974 | AS93: 0.13235467 | AT93: 0.16526042 | AU93: 0.321198 | AV93: 0.52052427 | AW93: 0.84393028 | AX93: 1.1497999 | AY93: 1.2792 | AZ93: 1.5571001 | BA93: 1.8200001 | BB93: 2.1300001 | BC93: 6 | BD93: 11.5 | BE93: 13.9432 | BF93: 16.4 | BG93: 18.860001 | BH93: 21.32 | BI93: 23.780001 | BJ93: 26.24 | BK93: 29.4 | BL93: 49.133701 | BM93: 55.001301 | BN93: 58.7173 | BO93: 63.6595 | BP93: 63.519501 | BQ93: 63.299301
A94: Greece | B94: GRC | C94: Individuals using the Internet (% of population) | D94: IT.NET.USER.ZS | AI94: 0 | AJ94: 0.0488 | AK94: 0.0483 | AL94: 0.191 | AM94: 0.378 | AN94: 0.75 | AO94: 1.4 | AP94: 1.85 | AQ94: 3.22 | AR94: 6.88 | AS94: 9.1388373 | AT94: 10.935026 | AU94: 14.67 | AV94: 17.8 | AW94: 21.42 | AX94: 24 | AY94: 32.25 | AZ94: 35.88 | BA94: 38.2 | BB94: 42.4 | BC94: 44.4 | BD94: 51.649995 | BE94: 55.069993 | BF94: 59.8663 | BG94: 63.20734 | BH94: 66.834959 | BI94: 69.087915 | BJ94: 69.892971 | BK94: 72.238373 | BL94: 75.671207 | BM94: 78.115845 | BN94: 78.494264 | BO94: 83.170663 | BP94: 85.010223 | BQ94: 86.269689
A95: Grenada | B95: GRD | C95: Individuals using the Internet (% of population) | D95: IT.NET.USER.ZS | AI95: 0 | AJ95: 0 | AK95: 0 | AL95: 0 | AM95: 0 | AN95: 0 | AO95: 0.298 | AP95: 0.991 | AQ95: 1.48 | AR95: 2.47 | AS95: 4.063908 | AT95: 5.128104 | AU95: 14.758841 | AV95: 18.645182 | AW95: 19.570621 | AX95: 20.487801 | AY95: 21.396 | AZ95: 22.29 | BA95: 23.18 | BB95: 24.049999 | BC95: 27 | BD95: 30 | BE95: 32 | BF95: 35 | BG95: 51.6 | BH95: 52.5 | BI95: 53.299999 | BJ95: 54.200001 | BK95: 61.424599 | BL95: 64.312798 | BM95: 65.653801 | BN95: 67.022797 | BO95: 68.420303 | BP95: 69.413101 | BQ95: 70.161598
A96: Greenland | B96: GRL | C96: Individuals using the Internet (% of population) | D96: IT.NET.USER.ZS | AI96: 0 | AM96: 0.0647 | AN96: 0.0539 | AO96: 1.8 | AP96: 7.95 | AQ96: 14.7 | AR96: 21.6 | AS96: 31.747811 | AT96: 35.464137 | AU96: 44.154789 | AV96: 54.53426 | AW96: 56.099015 | AX96: 57.703405 | AY96: 59.361687 | AZ96: 61.07 | BA96: 62.82 | BB96: 62.83 | BC96: 63 | BD96: 64 | BE96: 64.89601 | BF96: 65.8 | BG96: 66.7 | BH96: 67.600443 | BI96: 68.500874 | BJ96: 69.482462
A97: Guatemala | B97: GTM | C97: Individuals using the Internet (% of population) | D97: IT.NET.USER.ZS | AI97: 0 | AN97: 0.003 | AO97: 0.0195 | AP97: 0.0955 | AQ97: 0.467 | AR97: 0.593 | AS97: 0.7123329 | AT97: 1.7382018 | AU97: 3.3917463 | AV97: 4.5488549 | AW97: 5.1 | AX97: 5.6999998 | AY97: 6.5 | AZ97: 7.3000002 | BA97: 8.3000002 | BB97: 9.3000002 | BC97: 10.5 | BD97: 12.3 | BE97: 16 | BF97: 19.700001 | BG97: 23.4 | BH97: 28.805901 | BI97: 34.5093 | BJ97: 37.900002 | BK97: 41.5 | BL97: 44.40105 | BM97: 47.512299 | BN97: 50.841649 | BO97: 54.404301 | BP97: 56.7267 | BQ97: 60.221401
A98: Guam | B98: GUM | C98: Individuals using the Internet (% of population) | D98: IT.NET.USER.ZS | AI98: 0 | AM98: 0.348 | AN98: 0.66 | AO98: 1.36 | AP98: 2.34 | AQ98: 4.5 | AR98: 8.5 | AS98: 16.113127 | AT98: 25.380228 | AU98: 31.192294 | AV98: 33.716682 | AW98: 36.161788 | AX98: 38.559878 | AY98: 43.851443 | AZ98: 46.150474 | BA98: 48.418702 | BB98: 50.642028 | BC98: 54.04 | BD98: 57.7 | BE98: 61.534159 | BF98: 65.4 | BG98: 69.27 | BH98: 73.14 | BI98: 77.01 | BJ98: 80.505466
A99: Guyana | B99: GUY | C99: Individuals using the Internet (% of population) | D99: IT.NET.USER.ZS | AI99: 0 | AO99: 0.0659 | AP99: 0.132 | AQ99: 0.264 | AR99: 0.4 | AS99: 0.6 | AT99: 1 | AU99: 1.5 | AV99: 2.4 | AW99: 3.7 | AX99: 5.6999998 | AY99: 8.8999996 | AZ99: 13.8 | BA99: 18.2 | BB99: 23.9 | BC99: 29.9 | BD99: 30 | BE99: 30.5 | BF99: 31 | BG99: 32 | BH99: 34 | BI99: 35.66 | BJ99: 42.675301 | BK99: 48.5989 | BL99: 55.312698 | BM99: 62.953999 | BN99: 71.650902 | BO99: 76.562401 | BP99: 79.355301 | BQ99: 83.000801
A100: High income | B100: HIC | C100: Individuals using the Internet (% of population) | D100: IT.NET.USER.ZS | AX100: 52.9 | AY100: 55.7 | AZ100: 61.3 | BA100: 64 | BB100: 66.4 | BC100: 69 | BD100: 70.4 | BE100: 73.7 | BF100: 75.1 | BG100: 77 | BH100: 78.3 | BI100: 82.5 | BJ100: 84.2 | BK100: 86.3 | BL100: 87.5 | BM100: 88.4 | BN100: 90 | BO100: 91 | BP100: 91.9 | BQ100: 93 | BR100: 94.2
A101: Hong Kong SAR, China | B101: HKG | C101: Individuals using the Internet (% of population) | D101: IT.NET.USER.ZS | AI101: 0 | AJ101: 0.121 | AK101: 0.85 | AL101: 1.33 | AM101: 2.78 | AN101: 3.22 | AO101: 4.75 | AP101: 10.5 | AQ101: 14.5 | AR101: 21.2 | AS101: 27.827761 | AT101: 38.671403 | AU101: 43.082383 | AV101: 52.200043 | AW101: 56.39988 | AX101: 56.9 | AY101: 60.8 | AZ101: 64.8 | BA101: 66.7 | BB101: 69.4 | BC101: 72 | BD101: 72.199997 | BE101: 72.9 | BF101: 74.2 | BG101: 79.86627 | BH101: 84.948353 | BI101: 87.479415 | BJ101: 89.415945 | BK101: 90.507395 | BL101: 91.7434 | BM101: 92.413136 | BN101: 93.087158 | BO101: 95.613571 | BP101: 95.977819 | BQ101: 95.75537
...

Sheet Metadata - Countries
A1: Country Code | B1: Region | C1: IncomeGroup | D1: SpecialNotes | E1: TableName
A2: ABW | B2: Latin America & Caribbean | C2: High income | E2: Aruba
A3: AFE | D3: 26 countries, stretching from the Red Sea in the North to the Cape of Good Hope in the South (https://www.worldbank.org/en/region/afr/eastern-and-southern-africa) | E3: Africa Eastern and Southern
A4: AFG | B4: Middle East & North Africa | C4: Low income | D4: The reporting period for national accounts data is designated as either calendar year basis (CY) or fiscal year basis (FY). For this country, it is fiscal year-based (fiscal year-end: March 20). Also, an estimate (PA.NUS.ATLS) of the exchange rate covers the same period and thus differs from the official exchange rate (CY). In addition, the World Bank systematically assesses the appropriateness of official exchange rates as conversion factors. In this country, multiple or dual exchange rate activity exists and must be accounted for appropriately in underlying statistics. An alternative estimate (“alternative conversion factor” - PA.NUS.ATLS) is thus calculated as a weighted average of the different exchange rates in use in the country. Doing so better reflects economic reality and leads to more accurate cross-country comparisons and country classifications by income level. For this country, this applies to the period 1960-2006. Alternative conversion factors are used in the Atlas methodology and elsewhere in World Development Indicators as single-year conversion factors. | E4: Afghanistan
A5: AFW | D5: 22 countries, stretching from the westernmost point of Africa, across the equator, and partly along the Atlantic Ocean till the Republic of Congo in the South (https://www.worldbank.org/en/region/afr/western-and-central-africa) | E5: Africa Western and Central
A6: AGO | B6: Sub-Saharan Africa | C6: Lower middle income | D6: The World Bank systematically assesses the appropriateness of official exchange rates as conversion factors. In this country, multiple or dual exchange rate activity exists and must be accounted for appropriately in underlying statistics. An alternative estimate (“alternative conversion factor” - PA.NUS.ATLS) is thus calculated as a weighted average of the different exchange rates in use in the country. Doing so better reflects economic reality and leads to more accurate cross-country comparisons and country classifications by income level. For this country, this applies to the period 1994-2025. Alternative conversion factors are used in the Atlas methodology and elsewhere in World Development Indicators as single-year conversion factors. | E6: Angola
A7: ALB | B7: Europe & Central Asia | C7: Upper middle income | E7: Albania
A8: AND | B8: Europe & Central Asia | C8: High income | E8: Andorra
A9: ARB | D9: Arab World aggregate. Arab World is composed of members of the League of Arab States. | E9: Arab World
A10: ARE | B10: Middle East & North Africa | C10: High income | E10: United Arab Emirates
A11: ARG | B11: Latin America & Caribbean | C11: Upper middle income | D11: Due to the limitations of the Atlas method in classifying countries experiencing persistent high inflation, this economy remains classified as upper-middle-income. The World Bank systematically assesses the appropriateness of official exchange rates as conversion factors. In this country, multiple or dual exchange rate activity exists and must be accounted for appropriately in underlying statistics. An alternative estimate (“alternative conversion factor” - PA.NUS.ATLS) is thus calculated as a weighted average of the different exchange rates in use in the country. Doing so better reflects economic reality and leads to more accurate cross-country comparisons and country classifications by income level. For this country, this applies to the period 1971-2018. Alternative conversion factors are used in the Atlas methodology and elsewhere in World Development Indicators as single-year conversion factors. | E11: Argentina
A12: ARM | B12: Europe & Central Asia | C12: Upper middle income | E12: Armenia
A13: ASM | B13: East Asia & Pacific | C13: High income | E13: American Samoa
A14: ATG | B14: Latin America & Caribbean | C14: High income | E14: Antigua and Barbuda
A15: AUS | B15: East Asia & Pacific | C15: High income | D15: The reporting period for national accounts data is designated as either calendar year basis (CY) or fiscal year basis (FY). For this country, it is fiscal year-based (fiscal year-end: June 30). Also, an estimate (PA.NUS.ATLS) of the exchange rate covers the same period and thus differs from the official exchange rate (CY). | E15: Australia
A16: AUT | B16: Europe & Central Asia | C16: High income | D16: A simple multiplier is used to convert the national currencies of EMU members to euros. The following irrevocable euro conversion rate was adopted by the EU Council on January 1, 1999: 1 euro = 13.7603 Austrian schilling. Please note that historical data before 1999 are not actual euros and are not comparable or suitable for aggregation across countries. | E16: Austria
A17: AZE | B17: Europe & Central Asia | C17: Upper middle income | E17: Azerbaijan
A18: BDI | B18: Sub-Saharan Africa | C18: Low income | D18: The World Bank systematically assesses the appropriateness of official exchange rates as conversion factors. In this country, multiple or dual exchange rate activity exists and must be accounted for appropriately in underlying statistics. An alternative estimate (“alternative conversion factor” - PA.NUS.ATLS) is thus calculated as a weighted average of the different exchange rates in use in the country. Doing so better reflects economic reality and leads to more accurate cross-country comparisons and country classifications by income level. For this country, this applies to the period 1983-2025. Alternative conversion factors are used in the Atlas methodology and elsewhere in World Development Indicators as single-year conversion factors. | E18: Burundi
A19: BEL | B19: Europe & Central Asia | C19: High income | D19: A simple multiplier is used to convert the national currencies of EMU members to euros. The following irrevocable euro conversion rate was adopted by the EU Council on January 1, 1999: 1 euro = 40.3399 Belgian franc. Please note that historical data before 1999 are not actual euros and are not comparable or suitable for aggregation across countries. | E19: Belgium
A20: BEN | B20: Sub-Saharan Africa | C20: Lower middle income | E20: Benin
A21: BFA | B21: Sub-Saharan Africa | C21: Low income | E21: Burkina Faso
A22: BGD | B22: South Asia | C22: Lower middle income | D22: The reporting period for national accounts data is designated as either calendar year basis (CY) or fiscal year basis (FY). For this country, it is fiscal year-based (fiscal year-end: June 30). Also, an estimate (PA.NUS.ATLS) of the exchange rate covers the same period and thus differs from the official exchange rate (CY). | E22: Bangladesh
A23: BGR | B23: Europe & Central Asia | C23: High income | D23: A simple multiplier is used to convert the national currencies of EMU members to euros. The following irrevocable euro conversion rate entered into force on January 1, 2026: 1 euro = 1.95583 Bulgarian Lev. Please note that historical data are not actual euros and are not comparable or suitable for aggregation across countries. | E23: Bulgaria
A24: BHR | B24: Middle East & North Africa | C24: High income | E24: Bahrain
A25: BHS | B25: Latin America & Caribbean | C25: High income | E25: Bahamas, The
A26: BIH | B26: Europe & Central Asia | C26: Upper middle income | E26: Bosnia and Herzegovina
A27: BLR | B27: Europe & Central Asia | C27: Upper middle income | D27: Data before 2015 were adjusted to reflect the new denomination effective from July 1, 2016 (BYN), a decrease of 10,000 times (1 BYN = 10,000 BYR) | E27: Belarus
A28: BLZ | B28: Latin America & Caribbean | C28: Upper middle income | E28: Belize
A29: BMU | B29: North America | C29: High income | E29: Bermuda
A30: BOL | B30: Latin America & Caribbean | C30: Lower middle income | E30: Bolivia
A31: BRA | B31: Latin America & Caribbean | C31: Upper middle income | E31: Brazil
A32: BRB | B32: Latin America & Caribbean | C32: High income | E32: Barbados
A33: BRN | B33: East Asia & Pacific | C33: High income | E33: Brunei Darussalam
A34: BTN | B34: South Asia | C34: Lower middle income | E34: Bhutan
A35: BWA | B35: Sub-Saharan Africa | C35: Upper middle income | E35: Botswana
A36: CAF | B36: Sub-Saharan Africa | C36: Low income | E36: Central African Republic
A37: CAN | B37: North America | C37: High income | D37: Fiscal year end: March 31; reporting period for national accounts data: CY. | E37: Canada
A38: CEB | D38: Central Europe and the Baltics aggregate. | E38: Central Europe and the Baltics
A39: CHE | B39: Europe & Central Asia | C39: High income | E39: Switzerland
A40: CHI | B40: Europe & Central Asia | C40: High income | E40: Channel Islands
A41: CHL | B41: Latin America & Caribbean | C41: High income | E41: Chile
A42: CHN | B42: East Asia & Pacific | C42: Upper middle income | D42: On 1 July 1997 China resumed its exercise of sovereignty over Hong Kong, and on 20 December 1999, China resumed its exercise of sovereignty over Macao. Unless otherwise noted, data for China do not include data for Hong Kong SAR, China; Macao SAR, China; or Taiwan, China. The World Bank systematically assesses the appropriateness of official exchange rates as conversion factors. In this country, multiple or dual exchange rate activity exists and must be accounted for appropriately in underlying statistics. An alternative estimate (“alternative conversion factor” - PA.NUS.ATLS) is thus calculated as a weighted average of the different exchange rates in use in the country. Doing so better reflects economic reality and leads to more accurate cross-country comparisons and country classifications by income level. For this country, this applies to the period 1978-1993. Alternative conversion factors are used in the Atlas methodology and elsewhere in World Development Indicators as single-year conversion factors. | E42: China
A43: CIV | B43: Sub-Saharan Africa | C43: Lower middle income | E43: Côte d'Ivoire
A44: CMR | B44: Sub-Saharan Africa | C44: Lower middle income | E44: Cameroon
A45: COD | B45: Sub-Saharan Africa | C45: Low income | D45: The World Bank systematically assesses the appropriateness of official exchange rates as conversion factors. In this country, multiple or dual exchange rate activity exists and must be accounted for appropriately in underlying statistics. An alternative estimate (“alternative conversion factor” - PA.NUS.ATLS) is thus calculated as a weighted average of the different exchange rates in use in the country. Doing so better reflects economic reality and leads to more accurate cross-country comparisons and country classifications by income level. For this country, this applies to the period 1999-2004. Alternative conversion factors are used in the Atlas methodology and elsewhere in World Development Indicators as single-year conversion factors. | E45: Congo, Dem. Rep.
A46: COG | B46: Sub-Saharan Africa | C46: Lower middle income | E46: Congo, Rep.
A47: COL | B47: Latin America & Caribbean | C47: Upper middle income | E47: Colombia
A48: COM | B48: Sub-Saharan Africa | C48: Lower middle income | E48: Comoros
A49: CPV | B49: Sub-Saharan Africa | C49: Upper middle income | E49: Cabo Verde
A50: CRI | B50: Latin America & Caribbean | C50: High income | E50: Costa Rica
A51: CSS | D51: Caribbean small states aggregate. | E51: Caribbean small states
A52: CUB | B52: Latin America & Caribbean | C52: Upper middle income | E52: Cuba
A53: CUW | B53: Latin America & Caribbean | C53: High income | E53: Curaçao
A54: CYM | B54: Latin America & Caribbean | C54: High income | E54: Cayman Islands
A55: CYP | B55: Europe & Central Asia | C55: High income | D55: A simple multiplier is used to convert the national currencies of EMU members to euros. The following irrevocable euro conversion rate entered into force on January 1, 2008: 1 euro = 0.585274 Cyprus pounds. Please note that historical data are not actual euros and are not comparable or suitable for aggregation across countries. | E55: Cyprus
A56: CZE | B56: Europe & Central Asia | C56: High income | E56: Czechia
A57: DEU | B57: Europe & Central Asia | C57: High income | D57: A simple multiplier is used to convert the national currencies of EMU members to euros. The following irrevocable euro conversion rate was adopted by the EU Council on January 1, 1999: 1 euro = 1.95583 Deutsche Mark. Please note that historical data before 1999 are not actual euros and are not comparable or suitable for aggregation across countries. GDP data before 1991 are calculated by applying backward GDP growth rates of the former Federal Republic of Germany starting from the first official GDP value for the unified Germany (1991). | E57: Germany
A58: DJI | B58: Middle East & North Africa | C58: Lower middle income | E58: Djibouti
A59: DMA | B59: Latin America & Caribbean | C59: Upper middle income | E59: Dominica
A60: DNK | B60: Europe & Central Asia | C60: High income | E60: Denmark
A61: DOM | B61: Latin America & Caribbean | C61: Upper middle income | E61: Dominican Republic
A62: DZA | B62: Middle East & North Africa | C62: Upper middle income | E62: Algeria
A63: EAP | E63: East Asia & Pacific (excluding high income)
A64: EAR | D64: Early-dividend countries are mostly lower-middle-income countries further along the fertility transition. Fertility rates have fallen below four births per woman and the working-age share of the population is likely rising considerably. | E64: Early-demographic dividend
A65: EAS | D65: East Asia and Pacific regional aggregate (includes all income levels). | E65: East Asia & Pacific
A66: ECA | E66: Europe & Central Asia (excluding high income)
A67: ECS | D67: Europe and Central Asia regional aggregate (includes all income levels). | E67: Europe & Central Asia
A68: ECU | B68: Latin America & Caribbean | C68: Upper middle income | E68: Ecuador
A69: EGY | B69: Middle East & North Africa | C69: Lower middle income | D69: The reporting period for national accounts data is designated as either calendar year basis (CY) or fiscal year basis (FY). For this country, it is fiscal year-based (fiscal year-end: June 30) for the years 1980 and after. The data from 1973 to 1979 refer to the calendar year data. Also, an estimate (PA.NUS.ATLS) of the exchange rate covers the same period and thus differs from the official exchange rate (CY). In addition, the World Bank systematically assesses the appropriateness of official exchange rates as conversion factors. In this country, multiple or dual exchange rate activity exists and must be accounted for appropriately in underlying statistics. An alternative estimate (“alternative conversion factor” - PA.NUS.ATLS) is thus calculated as a weighted average of the different exchange rates in use in the country. Doing so better reflects economic reality and leads to more accurate cross-country comparisons and country classifications by income level. For this country, this applies to the period 1965-2021. Alternative conversion factors are used in the Atlas methodology and elsewhere in World Development Indicators as single-year conversion factors. The national accounts data for Egypt has been updated to reflect local constant prices in the year 2022, moving from the previous reference of 2017. | E69: Egypt, Arab Rep.
A70: EMU | D70: Euro area aggregate. | E70: Euro area
A71: ERI | B71: Sub-Saharan Africa | C71: Low income | D71: The World Bank systematically assesses the appropriateness of official exchange rates as conversion factors. In this country, multiple or dual exchange rate activity exists and must be accounted for appropriately in underlying statistics. An alternative estimate (“alternative conversion factor” - PA.NUS.ATLS) is thus calculated as a weighted average of the different exchange rates in use in the country. Doing so better reflects economic reality and leads to more accurate cross-country comparisons and country classifications by income level. For this country, this applies to the period 1992-1997. Alternative conversion factors are used in the Atlas methodology and elsewhere in World Development Indicators as single-year conversion factors. | E71: Eritrea
A72: ESP | B72: Europe & Central Asia | C72: High income | D72: A simple multiplier is used to convert the national currencies of EMU members to euros. The following irrevocable euro conversion rate was adopted by the EU Council on January 1, 1999: 1 euro = 166.386 Spanish peseta. Please note that historical data before 1999 are not actual euros and are not comparable or suitable for aggregation across countries. | E72: Spain
A73: EST | B73: Europe & Central Asia | C73: High income | D73: The following irrevocable euro conversion rate entered into force on January 1, 2011: 1 euro = 15.6466 Estonian kroon. Please note that historical data are not actual euros and are not comparable or suitable for aggregation across countries. | E73: Estonia
A74: ETH | B74: Sub-Saharan Africa | C74: Low income | D74: The reporting period for national accounts data is designated as either calendar year basis (CY) or fiscal year basis (FY). For this country, it is fiscal year-based (fiscal year-end: July 7). Also, an estimate (PA.NUS.ATLS) of the exchange rate covers the same period and thus differs from the official exchange rate (CY). The World Bank systematically assesses the appropriateness of official exchange rates as conversion factors. In this country, multiple or dual exchange rate activity exists and must be accounted for appropriately in underlying statistics. An alternative estimate (“alternative conversion factor” - PA.NUS.ATLS) is thus calculated by using an inflation-adjustment method. Doing so better reflects economic reality and leads to more accurate cross-country comparisons and country classifications by income level. For this country, this applies to the period 2015-2024. Alternative conversion factors are used in the Atlas methodology and elsewhere in World Development Indicators as single-year conversion factors. | E74: Ethiopia
A75: EUU | D75: European Union aggregate. | E75: European Union
A76: FCV | D76: Fragility, Conflict, and Violence (FCV) situations has replaced the previous FCS (Fragile and Conflict-Affected Situations) terminology. Until FY2027, a single Harmonized List of Fragile Situations combined "conflict" and "institutional" fragility. As of July 2026, the public FCV list includes countries where at least 20% of the population lives in areas with high conflict-related fatalities during a reference period. Along with a separted institutional fragility list, more information is available at: https://www.worldbank.org/en/topic/fragilityconflictviolence/brief/classification-of-fragile-and-conflict-affected-situations. | E76: Fragility, Conflict, and Violence (FCV) situations
A77: FIN | B77: Europe & Central Asia | C77: High income | D77: A simple multiplier is used to convert the national currencies of EMU members to euros. The following irrevocable euro conversion rate was adopted by the EU Council on January 1, 1999: 1 euro = 5.94573 Finnish markka. Please note that historical data before 1999 are not actual euros and are not comparable or suitable for aggregation across countries. | E77: Finland
A78: FJI | B78: East Asia & Pacific | C78: Upper middle income | E78: Fiji
A79: FRA | B79: Europe & Central Asia | C79: High income | D79: The following irrevocable euro conversion rate was adopted by the EU Council on January 1, 1999: 1 euro = 6.55957 French franc. Please note that historical data before 1999 are not actual euros and are not comparable or suitable for aggregation across countries. | E79: France
A80: FRO | B80: Europe & Central Asia | C80: High income | E80: Faroe Islands
A81: FSM | B81: East Asia & Pacific | C81: Upper middle income | D81: Fiscal year ends on September 30; reporting period for national accounts data: FY. The source for national accounts data is the Pacific and Virgin Islands Training Initiative. | E81: Micronesia, Fed. Sts.
A82: GAB | B82: Sub-Saharan Africa | C82: Upper middle income | E82: Gabon
A83: GBR | B83: Europe & Central Asia | C83: High income | E83: United Kingdom
A84: GEO | B84: Europe & Central Asia | C84: Upper middle income | D84: Includes self-governed areas only, which mostly exclude Abkhazia and South Ossetia, but small areas in Abkhazia and South Ossetia are included before 2008 or 2009 because of the changes in self-governed areas. | E84: Georgia
A85: GHA | B85: Sub-Saharan Africa | C85: Lower middle income | D85: The World Bank systematically assesses the appropriateness of official exchange rates as conversion factors. In this country, multiple or dual exchange rate activity exists and must be accounted for appropriately in underlying statistics. An alternative estimate (“alternative conversion factor” - PA.NUS.ATLS) is thus calculated as a weighted average of the different exchange rates in use in the country. Doing so better reflects economic reality and leads to more accurate cross-country comparisons and country classifications by income level. For this country, this applies to the period 1974-1987. Alternative conversion factors are used in the Atlas methodology and elsewhere in World Development Indicators as single-year conversion factors. | E85: Ghana
A86: GIB | B86: Europe & Central Asia | C86: High income | D86: The DEC conversion is not reported when national accounts data are unavailable. | E86: Gibraltar
A87: GIN | B87: Sub-Saharan Africa | C87: Lower middle income | E87: Guinea
A88: GMB | B88: Sub-Saharan Africa | C88: Low income | E88: Gambia, The
A89: GNB | B89: Sub-Saharan Africa | C89: Low income | E89: Guinea-Bissau
A90: GNQ | B90: Sub-Saharan Africa | C90: Upper middle income | E90: Equatorial Guinea
A91: GRC | B91: Europe & Central Asia | C91: High income | D91: A simple multiplier is used to convert the national currencies of EMU members to euros. The following irrevocable euro conversion rate was adopted by the EU Council on January 1, 1999: 1 euro = 340.75 Greek drachma. Please note that historical data before 1999 are not actual euros and are not comparable or suitable for aggregation across countries. | E91: Greece
A92: GRD | B92: Latin America & Caribbean | C92: Upper middle income | E92: Grenada
A93: GRL | B93: Europe & Central Asia | C93: High income | E93: Greenland
A94: GTM | B94: Latin America & Caribbean | C94: Upper middle income | D94: The World Bank systematically assesses the appropriateness of official exchange rates as conversion factors. In this country, multiple or dual exchange rate activity exists and must be accounted for appropriately in underlying statistics. An alternative estimate (“alternative conversion factor” - PA.NUS.ATLS) is thus calculated as a weighted average of the different exchange rates in use in the country. Doing so better reflects economic reality and leads to more accurate cross-country comparisons and country classifications by income level. For this country, this applies to the period 1985-2003. Alternative conversion factors are used in the Atlas methodology and elsewhere in World Development Indicators as single-year conversion factors. | E94: Guatemala
A95: GUM | B95: East Asia & Pacific | C95: High income | E95: Guam
A96: GUY | B96: Latin America & Caribbean | C96: High income | E96: Guyana
A97: HIC | D97: For FY27 (July 1, 2026–June 30, 2027), income groups are defined using 2025 GNI per capita (Atlas method): low income (LIC) ($1,175 or less); lower middle income (LMC) ($1,176–$4,635); upper middle income (UMC) ($4,636–$14,375); and high income (HIC) (above $14,375). “Low- and middle-income (LMY)” economies include low-, lower middle-, and upper middle-income groups, while “middle-income (MIC)” economies include lower middle- and upper middle-income groups. | E97: High income
A98: HKG | B98: East Asia & Pacific | C98: High income | D98: On 1 July 1997 China resumed its exercise of sovereignty over Hong Kong. Unless otherwise noted, data for China do not include data for Hong Kong SAR, China; Macao SAR, China; or Taiwan, China. Agriculture value added includes mining and quarrying. | E98: Hong Kong SAR, China
A99: HND | B99: Latin America & Caribbean | C99: Lower middle income | D99: The World Bank systematically assesses the appropriateness of official exchange rates as conversion factors. In this country, multiple or dual exchange rate activity exists and must be accounted for appropriately in underlying statistics. An alternative estimate (“alternative conversion factor” - PA.NUS.ATLS) is thus calculated as a weighted average of the different exchange rates in use in the country. Doing so better reflects economic reality and leads to more accurate cross-country comparisons and country classifications by income level. For this country, this applies to the period 1988-1989. Alternative conversion factors are used in the Atlas methodology and elsewhere in World Development Indicators as single-year conversion factors. | E99: Honduras
A100: HPC | D100: The Heavily Indebted Poor Countries (HIPC) Initiative, launched in 1996 by the IMF and World Bank, aims to reduce the external debt burdens of the most indebted poor countries. Most participants have completed the program, receiving a total of $76 billion in debt-service relief. For more information, visit https://www.imf.org/en/About/Factsheets/Sheets/2016/08/01/16/11/Debt-Relief-Under-the-Heavily-Indebted-Poor-Countries-Initiative. Data presented are aggregates for HIPC countries. | E100: Heavily indebted poor countries (HIPC)
...

Sheet Metadata - Indicators
A1: INDICATOR_CODE | B1: INDICATOR_NAME | C1: SOURCE_NOTE | D1: SOURCE_ORGANIZATION
A2: IT.NET.USER.ZS | B2: Individuals using the Internet (% of population) | C2: Internet users are individuals who have used the Internet (from any location) in the last 3 months. The Internet can be used via a computer, mobile phone, personal digital assistant, games machine, digital TV etc. | D2: World Telecommunication/ICT Indicators Database, International Telecommunication Union (ITU), uri: https://datahub.itu.int/

Sheet WB_CLEAN
A1: Country Name | B1: Country Code | C1: Region | D1: Internet Use (%) | E1: Include?
A2: Aruba | B2: ABW | C2: =_xlfn.XLOOKUP(B2,'Metadata - Countries'!A:A,'Metadata - Countries'!B:B,"Not found") -> Latin America & Caribbean | E2: =IF(AND(C2<>"",C2<>0,D2<>""),"Include","Exclude") -> Exclude
A3: Africa Eastern and Southern | B3: AFE | C3: =_xlfn.XLOOKUP(B3,'Metadata - Countries'!A:A,'Metadata - Countries'!B:B,"Not found") -> 0 | D3: 21.6 | E3: =IF(AND(C3<>"",C3<>0,D3<>""),"Include","Exclude") -> Exclude
A4: Afghanistan | B4: AFG | C4: =_xlfn.XLOOKUP(B4,'Metadata - Countries'!A:A,'Metadata - Countries'!B:B,"Not found") -> Middle East & North Africa | D4: 17.6 | E4: =IF(AND(C4<>"",C4<>0,D4<>""),"Include","Exclude") -> Include
A5: Africa Western and Central | B5: AFW | C5: =_xlfn.XLOOKUP(B5,'Metadata - Countries'!A:A,'Metadata - Countries'!B:B,"Not found") -> 0 | D5: 28.5 | E5: =IF(AND(C5<>"",C5<>0,D5<>""),"Include","Exclude") -> Exclude
A6: Angola | B6: AGO | C6: =_xlfn.XLOOKUP(B6,'Metadata - Countries'!A:A,'Metadata - Countries'!B:B,"Not found") -> Sub-Saharan Africa | D6: 32.129398 | E6: =IF(AND(C6<>"",C6<>0,D6<>""),"Include","Exclude") -> Include
A7: Albania | B7: ALB | C7: =_xlfn.XLOOKUP(B7,'Metadata - Countries'!A:A,'Metadata - Countries'!B:B,"Not found") -> Europe & Central Asia | D7: 68.550391 | E7: =IF(AND(C7<>"",C7<>0,D7<>""),"Include","Exclude") -> Include
A8: Andorra | B8: AND | C8: =_xlfn.XLOOKUP(B8,'Metadata - Countries'!A:A,'Metadata - Countries'!B:B,"Not found") -> Europe & Central Asia | D8: 90.718697 | E8: =IF(AND(C8<>"",C8<>0,D8<>""),"Include","Exclude") -> Include
A9: Arab World | B9: ARB | C9: =_xlfn.XLOOKUP(B9,'Metadata - Countries'!A:A,'Metadata - Countries'!B:B,"Not found") -> 0 | E9: =IF(AND(C9<>"",C9<>0,D9<>""),"Include","Exclude") -> Exclude
A10: United Arab Emirates | B10: ARE | C10: =_xlfn.XLOOKUP(B10,'Metadata - Countries'!A:A,'Metadata - Countries'!B:B,"Not found") -> Middle East & North Africa | D10: 99.149998 | E10: =IF(AND(C10<>"",C10<>0,D10<>""),"Include","Exclude") -> Include
A11: Argentina | B11: ARG | C11: =_xlfn.XLOOKUP(B11,'Metadata - Countries'!A:A,'Metadata - Countries'!B:B,"Not found") -> Latin America & Caribbean | D11: 79.946952 | E11: =IF(AND(C11<>"",C11<>0,D11<>""),"Include","Exclude") -> Include
A12: Armenia | B12: ARM | C12: =_xlfn.XLOOKUP(B12,'Metadata - Countries'!A:A,'Metadata - Countries'!B:B,"Not found") -> Europe & Central Asia | D12: 66.54395 | E12: =IF(AND(C12<>"",C12<>0,D12<>""),"Include","Exclude") -> Include
A13: American Samoa | B13: ASM | C13: =_xlfn.XLOOKUP(B13,'Metadata - Countries'!A:A,'Metadata - Countries'!B:B,"Not found") -> East Asia & Pacific | E13: =IF(AND(C13<>"",C13<>0,D13<>""),"Include","Exclude") -> Exclude
A14: Antigua and Barbuda | B14: ATG | C14: =_xlfn.XLOOKUP(B14,'Metadata - Countries'!A:A,'Metadata - Countries'!B:B,"Not found") -> Latin America & Caribbean | D14: 71.092598 | E14: =IF(AND(C14<>"",C14<>0,D14<>""),"Include","Exclude") -> Include
A15: Australia | B15: AUS | C15: =_xlfn.XLOOKUP(B15,'Metadata - Countries'!A:A,'Metadata - Countries'!B:B,"Not found") -> East Asia & Pacific | D15: 93.609901 | E15: =IF(AND(C15<>"",C15<>0,D15<>""),"Include","Exclude") -> Include
A16: Austria | B16: AUT | C16: =_xlfn.XLOOKUP(B16,'Metadata - Countries'!A:A,'Metadata - Countries'!B:B,"Not found") -> Europe & Central Asia | D16: 87.752205 | E16: =IF(AND(C16<>"",C16<>0,D16<>""),"Include","Exclude") -> Include
A17: Azerbaijan | B17: AZE | C17: =_xlfn.XLOOKUP(B17,'Metadata - Countries'!A:A,'Metadata - Countries'!B:B,"Not found") -> Europe & Central Asia | D17: 81.099999 | E17: =IF(AND(C17<>"",C17<>0,D17<>""),"Include","Exclude") -> Include
A18: Burundi | B18: BDI | C18: =_xlfn.XLOOKUP(B18,'Metadata - Countries'!A:A,'Metadata - Countries'!B:B,"Not found") -> Sub-Saharan Africa | D18: 6.0721998 | E18: =IF(AND(C18<>"",C18<>0,D18<>""),"Include","Exclude") -> Include
A19: Belgium | B19: BEL | C19: =_xlfn.XLOOKUP(B19,'Metadata - Countries'!A:A,'Metadata - Countries'!B:B,"Not found") -> Europe & Central Asia | D19: 90.275428 | E19: =IF(AND(C19<>"",C19<>0,D19<>""),"Include","Exclude") -> Include
A20: Benin | B20: BEN | C20: =_xlfn.XLOOKUP(B20,'Metadata - Countries'!A:A,'Metadata - Countries'!B:B,"Not found") -> Sub-Saharan Africa | D20: 20.500999 | E20: =IF(AND(C20<>"",C20<>0,D20<>""),"Include","Exclude") -> Include
A21: Burkina Faso | B21: BFA | C21: =_xlfn.XLOOKUP(B21,'Metadata - Countries'!A:A,'Metadata - Countries'!B:B,"Not found") -> Sub-Saharan Africa | D21: 9.271806 | E21: =IF(AND(C21<>"",C21<>0,D21<>""),"Include","Exclude") -> Include
A22: Bangladesh | B22: BGD | C22: =_xlfn.XLOOKUP(B22,'Metadata - Countries'!A:A,'Metadata - Countries'!B:B,"Not found") -> South Asia | D22: 30.383101 | E22: =IF(AND(C22<>"",C22<>0,D22<>""),"Include","Exclude") -> Include
A23: Bulgaria | B23: BGR | C23: =_xlfn.XLOOKUP(B23,'Metadata - Countries'!A:A,'Metadata - Countries'!B:B,"Not found") -> Europe & Central Asia | D23: 67.946981 | E23: =IF(AND(C23<>"",C23<>0,D23<>""),"Include","Exclude") -> Include
A24: Bahrain | B24: BHR | C24: =_xlfn.XLOOKUP(B24,'Metadata - Countries'!A:A,'Metadata - Countries'!B:B,"Not found") -> Middle East & North Africa | D24: 99.701504 | E24: =IF(AND(C24<>"",C24<>0,D24<>""),"Include","Exclude") -> Include
A25: Bahamas, The | B25: BHS | C25: =_xlfn.XLOOKUP(B25,'Metadata - Countries'!A:A,'Metadata - Countries'!B:B,"Not found") -> Latin America & Caribbean | D25: 90.693298 | E25: =IF(AND(C25<>"",C25<>0,D25<>""),"Include","Exclude") -> Include
... A28: Belize | B28: BLZ | C28: =_xlfn.XLOOKUP(B28,'Metadata - Countries'!A:A,'Metadata - Countries'!B:B,"Not found") -> Latin America & Caribbean | D28: 58.765202 | E28: =IF(AND(C28<>"",C28<>0,D28<>""),"Include","Exclude") -> Include
A29: Bermuda | B29: BMU | C29: =_xlfn.XLOOKUP(B29,'Metadata - Countries'!A:A,'Metadata - Countries'!B:B,"Not found") -> North America | E29: =IF(AND(C29<>"",C29<>0,D29<>""),"Include","Exclude") -> Exclude
A30: Bolivia | B30: BOL | C30: =_xlfn.XLOOKUP(B30,'Metadata - Countries'!A:A,'Metadata - Countries'!B:B,"Not found") -> Latin America & Caribbean | D30: 47.474819 | E30: =IF(AND(C30<>"",C30<>0,D30<>""),"Include","Exclude") -> Include
A31: Brazil | B31: BRA | C31: =_xlfn.XLOOKUP(B31,'Metadata - Countries'!A:A,'Metadata - Countries'!B:B,"Not found") -> Latin America & Caribbean | D31: 73.91244 | E31: =IF(AND(C31<>"",C31<>0,D31<>""),"Include","Exclude") -> Include
A32: Barbados | B32: BRB | C32: =_xlfn.XLOOKUP(B32,'Metadata - Countries'!A:A,'Metadata - Countries'!B:B,"Not found") -> Latin America & Caribbean | D32: 70.307098 | E32: =IF(AND(C32<>"",C32<>0,D32<>""),"Include","Exclude") -> Include
A33: Brunei Darussalam | B33: BRN | C33: =_xlfn.XLOOKUP(B33,'Metadata - Countries'!A:A,'Metadata - Countries'!B:B,"Not found") -> East Asia & Pacific | D33: 95 | E33: =IF(AND(C33<>"",C33<>0,D33<>""),"Include","Exclude") -> Include
A34: Bhutan | B34: BTN | C34: =_xlfn.XLOOKUP(B34,'Metadata - Countries'!A:A,'Metadata - Countries'!B:B,"Not found") -> South Asia | D34: 74.179398 | E34: =IF(AND(C34<>"",C34<>0,D34<>""),"Include","Exclude") -> Include
A35: Botswana | B35: BWA | C35: =_xlfn.XLOOKUP(B35,'Metadata - Countries'!A:A,'Metadata - Countries'!B:B,"Not found") -> Sub-Saharan Africa | D35: 48.8228 | E35: =IF(AND(C35<>"",C35<>0,D35<>""),"Include","Exclude") -> Include
A36: Central African Republic | B36: CAF | C36: =_xlfn.XLOOKUP(B36,'Metadata - Countries'!A:A,'Metadata - Countries'!B:B,"Not found") -> Sub-Saharan Africa | D36: 7.5092001 | E36: =IF(AND(C36<>"",C36<>0,D36<>""),"Include","Exclude") -> Include
A37: Canada | B37: CAN | C37: =_xlfn.XLOOKUP(B37,'Metadata - Countries'!A:A,'Metadata - Countries'!B:B,"Not found") -> North America | D37: 91.912903 | E37: =IF(AND(C37<>"",C37<>0,D37<>""),"Include","Exclude") -> Include
A38: Central Europe and the Baltics | B38: CEB | C38: =_xlfn.XLOOKUP(B38,'Metadata - Countries'!A:A,'Metadata - Countries'!B:B,"Not found") -> 0 | E38: =IF(AND(C38<>"",C38<>0,D38<>""),"Include","Exclude") -> Exclude
A39: Switzerland | B39: CHE | C39: =_xlfn.XLOOKUP(B39,'Metadata - Countries'!A:A,'Metadata - Countries'!B:B,"Not found") -> Europe & Central Asia | D39: 93.146087 | E39: =IF(AND(C39<>"",C39<>0,D39<>""),"Include","Exclude") -> Include
A40: Channel Islands | B40: CHI | C40: =_xlfn.XLOOKUP(B40,'Metadata - Countries'!A:A,'Metadata - Countries'!B:B,"Not found") -> Europe & Central Asia | E40: =IF(AND(C40<>"",C40<>0,D40<>""),"Include","Exclude") -> Exclude
A41: Chile | B41: CHL | C41: =_xlfn.XLOOKUP(B41,'Metadata - Countries'!A:A,'Metadata - Countries'!B:B,"Not found") -> Latin America & Caribbean | D41: 85.017601 | E41: =IF(AND(C41<>"",C41<>0,D41<>""),"Include","Exclude") -> Include
A42: China | B42: CHN | C42: =_xlfn.XLOOKUP(B42,'Metadata - Countries'!A:A,'Metadata - Countries'!B:B,"Not found") -> East Asia & Pacific | D42: 64.080881 | E42: =IF(AND(C42<>"",C42<>0,D42<>""),"Include","Exclude") -> Include
A43: Cote d'Ivoire | B43: CIV | C43: =_xlfn.XLOOKUP(B43,'Metadata - Countries'!A:A,'Metadata - Countries'!B:B,"Not found") -> Sub-Saharan Africa | D43: 36.288955 | E43: =IF(AND(C43<>"",C43<>0,D43<>""),"Include","Exclude") -> Include
A44: Cameroon | B44: CMR | C44: =_xlfn.XLOOKUP(B44,'Metadata - Countries'!A:A,'Metadata - Countries'!B:B,"Not found") -> Sub-Saharan Africa | D44: 36.5392 | E44: =IF(AND(C44<>"",C44<>0,D44<>""),"Include","Exclude") -> Include
A45: Congo, Dem. Rep. | B45: COD | C45: =_xlfn.XLOOKUP(B45,'Metadata - Countries'!A:A,'Metadata - Countries'!B:B,"Not found") -> Sub-Saharan Africa | D45: 13.0297 | E45: =IF(AND(C45<>"",C45<>0,D45<>""),"Include","Exclude") -> Include
A46: Congo, Rep. | B46: COG | C46: =_xlfn.XLOOKUP(B46,'Metadata - Countries'!A:A,'Metadata - Countries'!B:B,"Not found") -> Sub-Saharan Africa | D46: 16.1164 | E46: =IF(AND(C46<>"",C46<>0,D46<>""),"Include","Exclude") -> Include
A47: Colombia | B47: COL | C47: =_xlfn.XLOOKUP(B47,'Metadata - Countries'!A:A,'Metadata - Countries'!B:B,"Not found") -> Latin America & Caribbean | D47: 65.006901 | E47: =IF(AND(C47<>"",C47<>0,D47<>""),"Include","Exclude") -> Include
A48: Comoros | B48: COM | C48: =_xlfn.XLOOKUP(B48,'Metadata - Countries'!A:A,'Metadata - Countries'!B:B,"Not found") -> Sub-Saharan Africa | D48: 16.383801 | E48: =IF(AND(C48<>"",C48<>0,D48<>""),"Include","Exclude") -> Include
A49: Cabo Verde | B49: CPV | C49: =_xlfn.XLOOKUP(B49,'Metadata - Countries'!A:A,'Metadata - Countries'!B:B,"Not found") -> Sub-Saharan Africa | D49: 61.943398 | E49: =IF(AND(C49<>"",C49<>0,D49<>""),"Include","Exclude") -> Include
A50: Costa Rica | B50: CRI | C50: =_xlfn.XLOOKUP(B50,'Metadata - Countries'!A:A,'Metadata - Countries'!B:B,"Not found") -> Latin America & Caribbean | D50: 81.202596 | E50: =IF(AND(C50<>"",C50<>0,D50<>""),"Include","Exclude") -> Include
A51: Caribbean small states | B51: CSS | C51: =_xlfn.XLOOKUP(B51,'Metadata - Countries'!A:A,'Metadata - Countries'!B:B,"Not found") -> 0 | E51: =IF(AND(C51<>"",C51<>0,D51<>""),"Include","Exclude") -> Exclude
A52: Cuba | B52: CUB | C52: =_xlfn.XLOOKUP(B52,'Metadata - Countries'!A:A,'Metadata - Countries'!B:B,"Not found") -> Latin America & Caribbean | D52: 67.970809 | E52: =IF(AND(C52<>"",C52<>0,D52<>""),"Include","Exclude") -> Include
A53: Curacao | B53: CUW | C53: =_xlfn.XLOOKUP(B53,'Metadata - Countries'!A:A,'Metadata - Countries'!B:B,"Not found") -> Latin America & Caribbean | E53: =IF(AND(C53<>"",C53<>0,D53<>""),"Include","Exclude") -> Exclude
A54: Cayman Islands | B54: CYM | C54: =_xlfn.XLOOKUP(B54,'Metadata - Countries'!A:A,'Metadata - Countries'!B:B,"Not found") -> Latin America & Caribbean | E54: =IF(AND(C54<>"",C54<>0,D54<>""),"Include","Exclude") -> Exclude
A55: Cyprus | B55: CYP | C55: =_xlfn.XLOOKUP(B55,'Metadata - Countries'!A:A,'Metadata - Countries'!B:B,"Not found") -> Europe & Central Asia | D55: 86.06363 | E55: =IF(AND(C55<>"",C55<>0,D55<>""),"Include","Exclude") -> Include
A56: Czechia | B56: CZE | C56: =_xlfn.XLOOKUP(B56,'Metadata - Countries'!A:A,'Metadata - Countries'!B:B,"Not found") -> Europe & Central Asia | D56: 80.866944 | E56: =IF(AND(C56<>"",C56<>0,D56<>""),"Include","Exclude") -> Include
A57: Germany | B57: DEU | C57: =_xlfn.XLOOKUP(B57,'Metadata - Countries'!A:A,'Metadata - Countries'!B:B,"Not found") -> Europe & Central Asia | D57: 88.134517 | E57: =IF(AND(C57<>"",C57<>0,D57<>""),"Include","Exclude") -> Include
A58: Djibouti | B58: DJI | C58: =_xlfn.XLOOKUP(B58,'Metadata - Countries'!A:A,'Metadata - Countries'!B:B,"Not found") -> Middle East & North Africa | D58: 58.4762 | E58: =IF(AND(C58<>"",C58<>0,D58<>""),"Include","Exclude") -> Include
A59: Dominica | B59: DMA | C59: =_xlfn.XLOOKUP(B59,'Metadata - Countries'!A:A,'Metadata - Countries'!B:B,"Not found") -> Latin America & Caribbean | D59: 73.382004 | E59: =IF(AND(C59<>"",C59<>0,D59<>""),"Include","Exclude") -> Include
A60: Denmark | B60: DNK | C60: =_xlfn.XLOOKUP(B60,'Metadata - Countries'!A:A,'Metadata - Countries'!B:B,"Not found") -> Europe & Central Asia | D60: 98.046435 | E60: =IF(AND(C60<>"",C60<>0,D60<>""),"Include","Exclude") -> Include
A61: Dominican Republic | B61: DOM | C61: =_xlfn.XLOOKUP(B61,'Metadata - Countries'!A:A,'Metadata - Countries'!B:B,"Not found") -> Latin America & Caribbean | D61: 79.7155 | E61: =IF(AND(C61<>"",C61<>0,D61<>""),"Include","Exclude") -> Include
A62: Algeria | B62: DZA | C62: =_xlfn.XLOOKUP(B62,'Metadata - Countries'!A:A,'Metadata - Countries'!B:B,"Not found") -> Middle East & North Africa | D62: 55.790699 | E62: =IF(AND(C62<>"",C62<>0,D62<>""),"Include","Exclude") -> Include
A63: East Asia & Pacific (excluding high income) | B63: EAP | C63: =_xlfn.XLOOKUP(B63,'Metadata - Countries'!A:A,'Metadata - Countries'!B:B,"Not found") -> 0 | D63: 64 | E63: =IF(AND(C63<>"",C63<>0,D63<>""),"Include","Exclude") -> Exclude
A64: Early-demographic dividend | B64: EAR | C64: =_xlfn.XLOOKUP(B64,'Metadata - Countries'!A:A,'Metadata - Countries'!B:B,"Not found") -> 0 | E64: =IF(AND(C64<>"",C64<>0,D64<>""),"Include","Exclude") -> Exclude
A65: East Asia & Pacific | B65: EAS | C65: =_xlfn.XLOOKUP(B65,'Metadata - Countries'!A:A,'Metadata - Countries'!B:B,"Not found") -> 0 | D65: 67.1 | E65: =IF(AND(C65<>"",C65<>0,D65<>""),"Include","Exclude") -> Exclude
A66: Europe & Central Asia (excluding high income) | B66: ECA | C66: =_xlfn.XLOOKUP(B66,'Metadata - Countries'!A:A,'Metadata - Countries'!B:B,"Not found") -> 0 | D66: 70.3 | E66: =IF(AND(C66<>"",C66<>0,D66<>""),"Include","Exclude") -> Exclude
A67: Europe & Central Asia | B67: ECS | C67: =_xlfn.XLOOKUP(B67,'Metadata - Countries'!A:A,'Metadata - Countries'!B:B,"Not found") -> 0 | D67: 80.3 | E67: =IF(AND(C67<>"",C67<>0,D67<>""),"Include","Exclude") -> Exclude
A68: Ecuador | B68: ECU | C68: =_xlfn.XLOOKUP(B68,'Metadata - Countries'!A:A,'Metadata - Countries'!B:B,"Not found") -> Latin America & Caribbean | D68: 59.2 | E68: =IF(AND(C68<>"",C68<>0,D68<>""),"Include","Exclude") -> Include
A69: Egypt, Arab Rep. | B69: EGY | C69: =_xlfn.XLOOKUP(B69,'Metadata - Countries'!A:A,'Metadata - Countries'!B:B,"Not found") -> Middle East & North Africa | D69: 57.282866 | E69: =IF(AND(C69<>"",C69<>0,D69<>""),"Include","Exclude") -> Include
A70: Euro area | B70: EMU | C70: =_xlfn.XLOOKUP(B70,'Metadata - Countries'!A:A,'Metadata - Countries'!B:B,"Not found") -> 0 | E70: =IF(AND(C70<>"",C70<>0,D70<>""),"Include","Exclude") -> Exclude
A71: Eritrea | B71: ERI | C71: =_xlfn.XLOOKUP(B71,'Metadata - Countries'!A:A,'Metadata - Countries'!B:B,"Not found") -> Sub-Saharan Africa | D71: 11.2238 | E71: =IF(AND(C71<>"",C71<>0,D71<>""),"Include","Exclude") -> Include
A72: Spain | B72: ESP | C72: =_xlfn.XLOOKUP(B72,'Metadata - Countries'!A:A,'Metadata - Countries'!B:B,"Not found") -> Europe & Central Asia | D72: 90.718665 | E72: =IF(AND(C72<>"",C72<>0,D72<>""),"Include","Exclude") -> Include
A73: Estonia | B73: EST | C73: =_xlfn.XLOOKUP(B73,'Metadata - Countries'!A:A,'Metadata - Countries'!B:B,"Not found") -> Europe & Central Asia | D73: 90.228928 | E73: =IF(AND(C73<>"",C73<>0,D73<>""),"Include","Exclude") -> Include
A74: Ethiopia | B74: ETH | C74: =_xlfn.XLOOKUP(B74,'Metadata - Countries'!A:A,'Metadata - Countries'!B:B,"Not found") -> Sub-Saharan Africa | D74: 15.9846 | E74: =IF(AND(C74<>"",C74<>0,D74<>""),"Include","Exclude") -> Include
A75: European Union | B75: EUU | C75: =_xlfn.XLOOKUP(B75,'Metadata - Countries'!A:A,'Metadata - Countries'!B:B,"Not found") -> 0 | E75: =IF(AND(C75<>"",C75<>0,D75<>""),"Include","Exclude") -> Exclude
A76: Fragility, Conflict, and Violence (FCV) situations | B76: FCV | C76: =_xlfn.XLOOKUP(B76,'Metadata - Countries'!A:A,'Metadata - Countries'!B:B,"Not found") -> 0 | E76: =IF(AND(C76<>"",C76<>0,D76<>""),"Include","Exclude") -> Exclude
A77: Finland | B77: FIN | C77: =_xlfn.XLOOKUP(B77,'Metadata - Countries'!A:A,'Metadata - Countries'!B:B,"Not found") -> Europe & Central Asia | D77: 89.607385 | E77: =IF(AND(C77<>"",C77<>0,D77<>""),"Include","Exclude") -> Include
A78: Fiji | B78: FJI | C78: =_xlfn.XLOOKUP(B78,'Metadata - Countries'!A:A,'Metadata - Countries'!B:B,"Not found") -> East Asia & Pacific | D78: 63.217899 | E78: =IF(AND(C78<>"",C78<>0,D78<>""),"Include","Exclude") -> Include
A79: France | B79: FRA | C79: =_xlfn.XLOOKUP(B79,'Metadata - Countries'!A:A,'Metadata - Countries'!B:B,"Not found") -> Europe & Central Asia | D79: 83.339744 | E79: =IF(AND(C79<>"",C79<>0,D79<>""),"Include","Exclude") -> Include
A80: Faroe Islands | B80: FRO | C80: =_xlfn.XLOOKUP(B80,'Metadata - Countries'!A:A,'Metadata - Countries'!B:B,"Not found") -> Europe & Central Asia | E80: =IF(AND(C80<>"",C80<>0,D80<>""),"Include","Exclude") -> Exclude
A81: Micronesia, Fed. Sts. | B81: FSM | C81: =_xlfn.XLOOKUP(B81,'Metadata - Countries'!A:A,'Metadata - Countries'!B:B,"Not found") -> East Asia & Pacific | D81: 37.973701 | E81: =IF(AND(C81<>"",C81<>0,D81<>""),"Include","Exclude") -> Include
A82: Gabon | B82: GAB | C82: =_xlfn.XLOOKUP(B82,'Metadata - Countries'!A:A,'Metadata - Countries'!B:B,"Not found") -> Sub-Saharan Africa | D82: 59.517601 | E82: =IF(AND(C82<>"",C82<>0,D82<>""),"Include","Exclude") -> Include
A83: United Kingdom | B83: GBR | C83: =_xlfn.XLOOKUP(B83,'Metadata - Countries'!A:A,'Metadata - Countries'!B:B,"Not found") -> Europe & Central Asia | D83: 92.516629 | E83: =IF(AND(C83<>"",C83<>0,D83<>""),"Include","Exclude") -> Include
A84: Georgia | B84: GEO | C84: =_xlfn.XLOOKUP(B84,'Metadata - Countries'!A:A,'Metadata - Countries'!B:B,"Not found") -> Europe & Central Asia | D84: 68.846714 | E84: =IF(AND(C84<>"",C84<>0,D84<>""),"Include","Exclude") -> Include
A85: Ghana | B85: GHA | C85: =_xlfn.XLOOKUP(B85,'Metadata - Countries'!A:A,'Metadata - Countries'!B:B,"Not found") -> Sub-Saharan Africa | D85: 22.0732 | E85: =IF(AND(C85<>"",C85<>0,D85<>""),"Include","Exclude") -> Include
A86: Gibraltar | B86: GIB | C86: =_xlfn.XLOOKUP(B86,'Metadata - Countries'!A:A,'Metadata - Countries'!B:B,"Not found") -> Europe & Central Asia | E86: =IF(AND(C86<>"",C86<>0,D86<>""),"Include","Exclude") -> Exclude
A87: Guinea | B87: GIN | C87: =_xlfn.XLOOKUP(B87,'Metadata - Countries'!A:A,'Metadata - Countries'!B:B,"Not found") -> Sub-Saharan Africa | D87: 23.890499 | E87: =IF(AND(C87<>"",C87<>0,D87<>""),"Include","Exclude") -> Include
A88: Gambia, The | B88: GMB | C88: =_xlfn.XLOOKUP(B88,'Metadata - Countries'!A:A,'Metadata - Countries'!B:B,"Not found") -> Sub-Saharan Africa | D88: 31.118299 | E88: =IF(AND(C88<>"",C88<>0,D88<>""),"Include","Exclude") -> Include
A89: Guinea-Bissau | B89: GNB | C89: =_xlfn.XLOOKUP(B89,'Metadata - Countries'!A:A,'Metadata - Countries'!B:B,"Not found") -> Sub-Saharan Africa | D89: 17.921499 | E89: =IF(AND(C89<>"",C89<>0,D89<>""),"Include","Exclude") -> Include
A90: Equatorial Guinea | B90: GNQ | C90: =_xlfn.XLOOKUP(B90,'Metadata - Countries'!A:A,'Metadata - Countries'!B:B,"Not found") -> Sub-Saharan Africa | D90: 49.133701 | E90: =IF(AND(C90<>"",C90<>0,D90<>""),"Include","Exclude") -> Include
A91: Greece | B91: GRC | C91: =_xlfn.XLOOKUP(B91,'Metadata - Countries'!A:A,'Metadata - Countries'!B:B,"Not found") -> Europe & Central Asia | D91: 75.671207 | E91: =IF(AND(C91<>"",C91<>0,D91<>""),"Include","Exclude") -> Include
A92: Grenada | B92: GRD | C92: =_xlfn.XLOOKUP(B92,'Metadata - Countries'!A:A,'Metadata - Countries'!B:B,"Not found") -> Latin America & Caribbean | D92: 64.312798 | E92: =IF(AND(C92<>"",C92<>0,D92<>""),"Include","Exclude") -> Include
A93: Greenland | B93: GRL | C93: =_xlfn.XLOOKUP(B93,'Metadata - Countries'!A:A,'Metadata - Countries'!B:B,"Not found") -> Europe & Central Asia | E93: =IF(AND(C93<>"",C93<>0,D93<>""),"Include","Exclude") -> Exclude
A94: Guatemala | B94: GTM | C94: =_xlfn.XLOOKUP(B94,'Metadata - Countries'!A:A,'Metadata - Countries'!B:B,"Not found") -> Latin America & Caribbean | D94: 44.40105 | E94: =IF(AND(C94<>"",C94<>0,D94<>""),"Include","Exclude") -> Include
A95: Guam | B95: GUM | C95: =_xlfn.XLOOKUP(B95,'Metadata - Countries'!A:A,'Metadata - Countries'!B:B,"Not found") -> East Asia & Pacific | E95: =IF(AND(C95<>"",C95<>0,D95<>""),"Include","Exclude") -> Exclude
A96: Guyana | B96: GUY | C96: =_xlfn.XLOOKUP(B96,'Metadata - Countries'!A:A,'Metadata - Countries'!B:B,"Not found") -> Latin America & Caribbean | D96: 55.312698 | E96: =IF(AND(C96<>"",C96<>0,D96<>""),"Include","Exclude") -> Include
A97: High income | B97: HIC | C97: =_xlfn.XLOOKUP(B97,'Metadata - Countries'!A:A,'Metadata - Countries'!B:B,"Not found") -> 0 | D97: 87.5 | E97: =IF(AND(C97<>"",C97<>0,D97<>""),"Include","Exclude") -> Exclude
A98: Hong Kong SAR, China | B98: HKG | C98: =_xlfn.XLOOKUP(B98,'Metadata - Countries'!A:A,'Metadata - Countries'!B:B,"Not found") -> East Asia & Pacific | D98: 91.7434 | E98: =IF(AND(C98<>"",C98<>0,D98<>""),"Include","Exclude") -> Include
A99: Honduras | B99: HND | C99: =_xlfn.XLOOKUP(B99,'Metadata - Countries'!A:A,'Metadata - Countries'!B:B,"Not found") -> Latin America & Caribbean | D99: 39.388352 | E99: =IF(AND(C99<>"",C99<>0,D99<>""),"Include","Exclude") -> Include
A100: Heavily indebted poor countries (HIPC) | B100: HPC | C100: =_xlfn.XLOOKUP(B100,'Metadata - Countries'!A:A,'Metadata - Countries'!B:B,"Not found") -> 0 | E100: =IF(AND(C100<>"",C100<>0,D100<>""),"Include","Exclude") -> Exclude
A101: Croatia | B101: HRV | C101: =_xlfn.XLOOKUP(B101,'Metadata - Countries'!A:A,'Metadata - Countries'!B:B,"Not found") -> Europe & Central Asia | D101: 79.079784 | E101: =IF(AND(C101<>"",C101<>0,D101<>""),"Include","Exclude") -> Include
A102: Haiti | B102: HTI | C102: =_xlfn.XLOOKUP(B102,'Metadata - Countries'!A:A,'Metadata - Countries'!B:B,"Not found") -> Latin America & Caribbean | D102: 35.764099 | E102: =IF(AND(C102<>"",C102<>0,D102<>""),"Include","Exclude") -> Include
...

Sheet WB_ANALYSIS_DATA
A1: Country Name | B1: Country Code | C1: Region | D1: Internet Use (%) | F1: WB_ANALYSIS_DATA — Documentation
A2: Afghanistan | B2: AFG | C2: =_xlfn.XLOOKUP(B2,'Metadata - Countries'!A:A,'Metadata - Countries'!B:B,"Not found") -> Middle East & North Africa | D2: 17.6 | F2: Purpose: Prepare a country-level dataset for comparing Internet use across World Bank geographic regions in 2019.
A3: Angola | B3: AGO | C3: =_xlfn.XLOOKUP(B3,'Metadata - Countries'!A:A,'Metadata - Countries'!B:B,"Not found") -> Sub-Saharan Africa | D3: 32.129398 | F3: Source: World Bank, World Development Indicators
A4: Albania | B4: ALB | C4: =_xlfn.XLOOKUP(B4,'Metadata - Countries'!A:A,'Metadata - Countries'!B:B,"Not found") -> Europe & Central Asia | D4: 68.550391 | F4: Indicator code:
A5: Andorra | B5: AND | C5: =_xlfn.XLOOKUP(B5,'Metadata - Countries'!A:A,'Metadata - Countries'!B:B,"Not found") -> Europe & Central Asia | D5: 90.718697 | F5: IT.NET.USER.ZS
A6: United Arab Emirates | B6: ARE | C6: =_xlfn.XLOOKUP(B6,'Metadata - Countries'!A:A,'Metadata - Countries'!B:B,"Not found") -> Middle East & North Africa | D6: 99.149998
A7: Argentina | B7: ARG | C7: =_xlfn.XLOOKUP(B7,'Metadata - Countries'!A:A,'Metadata - Countries'!B:B,"Not found") -> Latin America & Caribbean | D7: 79.946952 | F7: Indicator: Individuals using the Internet (% of population)
A8: Armenia | B8: ARM | C8: =_xlfn.XLOOKUP(B8,'Metadata - Countries'!A:A,'Metadata - Countries'!B:B,"Not found") -> Europe & Central Asia | D8: 66.54395 | F8: Reference year: 2019
A9: Antigua and Barbuda | B9: ATG | C9: =_xlfn.XLOOKUP(B9,'Metadata - Countries'!A:A,'Metadata - Countries'!B:B,"Not found") -> Latin America & Caribbean | D9: 71.092598 | F9: Variables
A10: Australia | B10: AUS | C10: =_xlfn.XLOOKUP(B10,'Metadata - Countries'!A:A,'Metadata - Countries'!B:B,"Not found") -> East Asia & Pacific | D10: 93.609901 | F10: Country Name
A11: Austria | B11: AUT | C11: =_xlfn.XLOOKUP(B11,'Metadata - Countries'!A:A,'Metadata - Countries'!B:B,"Not found") -> Europe & Central Asia | D11: 87.752205 | F11: : Economy name as provided by the source.
A12: Azerbaijan | B12: AZE | C12: =_xlfn.XLOOKUP(B12,'Metadata - Countries'!A:A,'Metadata - Countries'!B:B,"Not found") -> Europe & Central Asia | D12: 81.099999 | F12: Country Code
A13: Burundi | B13: BDI | C13: =_xlfn.XLOOKUP(B13,'Metadata - Countries'!A:A,'Metadata - Countries'!B:B,"Not found") -> Sub-Saharan Africa | D13: 6.0721998 | F13: : World Bank economy code.
A14: Belgium | B14: BEL | C14: =_xlfn.XLOOKUP(B14,'Metadata - Countries'!A:A,'Metadata - Countries'!B:B,"Not found") -> Europe & Central Asia | D14: 90.275428 | F14: Region
A15: Benin | B15: BEN | C15: =_xlfn.XLOOKUP(B15,'Metadata - Countries'!A:A,'Metadata - Countries'!B:B,"Not found") -> Sub-Saharan Africa | D15: 20.500999 | F15: : Geographic region obtained from the country metadata.
A16: Burkina Faso | B16: BFA | C16: =_xlfn.XLOOKUP(B16,'Metadata - Countries'!A:A,'Metadata - Countries'!B:B,"Not found") -> Sub-Saharan Africa | D16: 9.271806 | F16: Internet Use (%)
A17: Bangladesh | B17: BGD | C17: =_xlfn.XLOOKUP(B17,'Metadata - Countries'!A:A,'Metadata - Countries'!B:B,"Not found") -> South Asia | D17: 30.383101 | F17: : Indicator value for 2019.
A18: Bulgaria | B18: BGR | C18: =_xlfn.XLOOKUP(B18,'Metadata - Countries'!A:A,'Metadata - Countries'!B:B,"Not found") -> Europe & Central Asia | D18: 67.946981 | F18: Inclusion rules
A19: Bahrain | B19: BHR | C19: =_xlfn.XLOOKUP(B19,'Metadata - Countries'!A:A,'Metadata - Countries'!B:B,"Not found") -> Middle East & North Africa | D19: 99.701504 | F19: 1 | G19: Include only individual economies with a verified geographic region.
A20: Bahamas, The | B20: BHS | C20: =_xlfn.XLOOKUP(B20,'Metadata - Countries'!A:A,'Metadata - Countries'!B:B,"Not found") -> Latin America & Caribbean | D20: 90.693298 | F20: 2 | G20: Include only valid numeric Internet-use observations for 2019.
A21: Bosnia and Herzegovina | B21: BIH | C21: =_xlfn.XLOOKUP(B21,'Metadata - Countries'!A:A,'Metadata - Countries'!B:B,"Not found") -> Europe & Central Asia | D21: 69.946348 | F21: 3 | G21: Exclude regional and income-group aggregates from country-level regional averages.
A22: Belarus | B22: BLR | C22: =_xlfn.XLOOKUP(B22,'Metadata - Countries'!A:A,'Metadata - Countries'!B:B,"Not found") -> Europe & Central Asia | D22: 82.789152 | F22: 4 | G22: Retain missing or unresolved observations in the source/cleaning worksheet for transparency, but exclude them from the analysis dataset.
A23: Belize | B23: BLZ | C23: =_xlfn.XLOOKUP(B23,'Metadata - Countries'!A:A,'Metadata - Countries'!B:B,"Not found") -> Latin America & Caribbean | D23: 58.765202 | F23: 5 | G23: Do not replace missing values with zero.
A24: Bolivia | B24: BOL | C24: =_xlfn.XLOOKUP(B24,'Metadata - Countries'!A:A,'Metadata - Countries'!B:B,"Not found") -> Latin America & Caribbean | D24: 47.474819 | F24: Analytical method
A25: Brazil | B25: BRA | C25: =_xlfn.XLOOKUP(B25,'Metadata - Countries'!A:A,'Metadata - Countries'!B:B,"Not found") -> Latin America & Caribbean | D25: 73.91244 | F25: Calculate the unweighted mean of available country-level Internet-use percentages by geographic region. Use minimum, maximum, and range to examine the spread of country observations.
A26: Barbados | B26: BRB | C26: =_xlfn.XLOOKUP(B26,'Metadata - Countries'!A:A,'Metadata - Countries'!B:B,"Not found") -> Latin America & Caribbean | D26: 70.307098 | F26: Limitations
A27: Brunei Darussalam | B27: BRN | C27: =_xlfn.XLOOKUP(B27,'Metadata - Countries'!A:A,'Metadata - Countries'!B:B,"Not found") -> East Asia & Pacific | D27: 95 | F27: The analysis is descriptive. Country-level averages are not population-weighted regional rates, and differences between regions do not establish causal relationships. Results depend on the coverage and completeness of the 2019 observations.
A28: Bhutan | B28: BTN | C28: =_xlfn.XLOOKUP(B28,'Metadata - Countries'!A:A,'Metadata - Countries'!B:B,"Not found") -> South Asia | D28: 74.179398 | F28: Reproducibility
A29: Botswana | B29: BWA | C29: =_xlfn.XLOOKUP(B29,'Metadata - Countries'!A:A,'Metadata - Countries'!B:B,"Not found") -> Sub-Saharan Africa | D29: 48.8228 | F29: Record the final number of included economies, the date the source data were downloaded, and any unresolved region classifications before publishing the results.
A30: Central African Republic | B30: CAF | C30: =_xlfn.XLOOKUP(B30,'Metadata - Countries'!A:A,'Metadata - Countries'!B:B,"Not found") -> Sub-Saharan Africa | D30: 7.5092001
A31: Canada | B31: CAN | C31: =_xlfn.XLOOKUP(B31,'Metadata - Countries'!A:A,'Metadata - Countries'!B:B,"Not found") -> North America | D31: 91.912903
A32: Switzerland | B32: CHE | C32: =_xlfn.XLOOKUP(B32,'Metadata - Countries'!A:A,'Metadata - Countries'!B:B,"Not found") -> Europe & Central Asia | D32: 93.146087
A33: Chile | B33: CHL | C33: =_xlfn.XLOOKUP(B33,'Metadata - Countries'!A:A,'Metadata - Countries'!B:B,"Not found") -> Latin America & Caribbean | D33: 85.017601
A34: China | B34: CHN | C34: =_xlfn.XLOOKUP(B34,'Metadata - Countries'!A:A,'Metadata - Countries'!B:B,"Not found") -> East Asia & Pacific | D34: 64.080881
A35: Cote d'Ivoire | B35: CIV | C35: =_xlfn.XLOOKUP(B35,'Metadata - Countries'!A:A,'Metadata - Countries'!B:B,"Not found") -> Sub-Saharan Africa | D35: 36.288955
A36: Cameroon | B36: CMR | C36: =_xlfn.XLOOKUP(B36,'Metadata - Countries'!A:A,'Metadata - Countries'!B:B,"Not found") -> Sub-Saharan Africa | D36: 36.5392
A37: Congo, Dem. Rep. | B37: COD | C37: =_xlfn.XLOOKUP(B37,'Metadata - Countries'!A:A,'Metadata - Countries'!B:B,"Not found") -> Sub-Saharan Africa | D37: 13.0297
A38: Congo, Rep. | B38: COG | C38: =_xlfn.XLOOKUP(B38,'Metadata - Countries'!A:A,'Metadata - Countries'!B:B,"Not found") -> Sub-Saharan Africa | D38: 16.1164
A39: Colombia | B39: COL | C39: =_xlfn.XLOOKUP(B39,'Metadata - Countries'!A:A,'Metadata - Countries'!B:B,"Not found") -> Latin America & Caribbean | D39: 65.006901
A40: Comoros | B40: COM | C40: =_xlfn.XLOOKUP(B40,'Metadata - Countries'!A:A,'Metadata - Countries'!B:B,"Not found") -> Sub-Saharan Africa | D40: 16.383801
A41: Cabo Verde | B41: CPV | C41: =_xlfn.XLOOKUP(B41,'Metadata - Countries'!A:A,'Metadata - Countries'!B:B,"Not found") -> Sub-Saharan Africa | D41: 61.943398
... A190: Zimbabwe | B190: ZWE | C190: =_xlfn.XLOOKUP(B190,'Metadata - Countries'!A:A,'Metadata - Countries'!B:B,"Not found") -> Sub-Saharan Africa | D190: 26.588301

Sheet WB_PIVOT
A2: Research Question: What was the average country-level Internet-use percentage in each World Bank geographic region in 2019?
A5: Region | B5: Average of Internet Use (%) | C5: Count of Country Code
A6: East Asia & Pacific | B6: 62.18299 | C6: 27
A7: Europe & Central Asia | B7: 81.040703 | C7: 51
A8: Latin America & Caribbean | B8: 64.770252 | C8: 34
A9: Middle East & North Africa | B9: 70.068157 | C9: 22
A10: North America | B10: 90.671594 | C10: 2
A11: South Asia | B11: 46.152201 | C11: 6
A12: Sub-Saharan Africa | B12: 27.190369 | C12: 47
A13: Grand Total | B13: 59.745547 | C13: 189
A16: Interpretation
A17: Finding: In 2019, North America had the highest average Internet-use percentage (90.68%), while Sub-Saharan Africa had the lowest at 27.2%.
A18: Interpretation: Internet use differed across geographic regions. Differences may reflect infrastructure, affordability, income, and access, but this descriptive analysis cannot identify the causes.
A20: Limitation: The figures represent an unweighted average of available country-level percentages, not the population-weighted Internet-use rate for each region. Countries with missing data are excluded.
A23: Research Question 2: Which regions show the greatest variation in Internet use across countries?
A25: Region | B25: Min of Internet Use (%)2 | C25: Max of Internet Use (%)3 | D25: Average of Internet Use (%)
A26: East Asia & Pacific | B26: 13.6242 | C26: 96.157579 | D26: 62.18299
A27: Europe & Central Asia | B27: 22.6863 | C27: 99.504941 | D27: 81.040703
A28: Latin America & Caribbean | B28: 35.764099 | C28: 90.693298 | D28: 64.770252
A29: Middle East & North Africa | B29: 17.070902 | C29: 99.701504 | D29: 70.068157
A30: North America | B30: 89.430285 | C30: 91.912903 | D30: 90.671594
A31: South Asia | B31: 29.5235 | C31: 77.469704 | D31: 46.152201
A32: Sub-Saharan Africa | B32: 2.7314 | C32: 76.634201 | D32: 27.190369
A33: Grand Total | B33: 2.7314 | C33: 99.701504 | D33: 59.745547
A36: Region | B36: Min of Internet Use (%)2 | C36: Max of Internet Use (%)3 | D36: Range
A37: East Asia & Pacific | B37: 13.6242 | C37: 96.157579 | D37: =C37-B37 -> 82.533379
A38: Europe & Central Asia | B38: 22.6863 | C38: 99.504941 | D38: =C38-B38 -> 76.818641
A39: Latin America & Caribbean | B39: 35.764099 | C39: 90.693298 | D39: =C39-B39 -> 54.929199
A40: Middle East & North Africa | B40: 17.070902 | C40: 99.701504 | D40: =C40-B40 -> 82.630603
A41: North America | B41: 89.430285 | C41: 91.912903 | D41: =C41-B41 -> 2.482618
A42: South Asia | B42: 29.5235 | C42: 77.469704 | D42: =C42-B42 -> 47.946203
A43: Sub-Saharan Africa | B43: 2.7314 | C43: 76.634201 | D43: =C43-B43 -> 73.902801
A45: Interpretation
A46: Finding: In 2019, Middle East & North Africa had the largest range in country-level Internet use, at 82.63 percentage points, while North America had the smallest range, at 2.49 percentage points.
A48: Interpretation: The results suggest that the gap between the highest- and lowest-Internet-use countries differed across regions. A larger range indicates greater separation between the two extremes, while a smaller range indicates that the extremes were closer together.
A51: Limitation: The range uses only the minimum and maximum values and ignores all countries between them. It can be influenced by extreme observations and does not establish the causes of regional differences. Missing country observations may also affect the calculated range.
A53: Research note: These are descriptive results for 2019. Avoid claiming that a region has greater overall inequality based on the range alone; standard deviation or interquartile range would provide additional information about the distribution.
A56: Research Question 3: Which countries have the highest and lowest Internet use within each region?
A58: Region | B58: Country Name | C58: Average of Internet Use (%)
A59: South Asia | B59: Maldives | C59: 77.469704
B60: Bhutan | C60: 74.179398
B61: Nepal | C61: 33.336601
B62: Sri Lanka | C62: 32.020901
B63: Bangladesh | C63: 30.383101
B64: India | C64: 29.5235
A65: South Asia Total | C65: 46.152201
A66: Grand Total | C66: 46.152201
A68: Interpretation
A69: Finding: Within South Asia, Maldivies had the highest observed Internet-use percentage at 77.47%, while Bangladesh had the lowest at 30.39%.
A70: Interpretation: Countries within the same geographic region can have substantially different levels of Internet use. Regional averages therefore do not describe every country's experience.
A72: Limitation: This comparison is descriptive. It cannot explain why countries differ, and results may be affected by missing country observations or differences in national circumstances.
