Workbook

Sheet Raw_Data
A1: Illustrative Area | B1: Year | C1: Internet Access (%) | D1: Fixed Broadband Subscriptions (per 100 people) | E1: Mobile Internet Use (%) | F1: Households Using Digital Services (%) | G1: Column1
A2: Central Sample | B2: 2024 | C2: 80 | D2: 35 | E2: 88 | F2: 49
A3: Central Sample | B3: 2023 | C3: 76 | D3: 31 | E3: 85 | F3: 45 | G3: hjpj,
A4: Central Sample | B4: 2022 | C4: 73 | D4: 28 | E4: 82 | F4: 41
A5: North Sample | B5: 2024 | C5: 70 | D5: 24 | E5: 80 | F5: 42
A6: North Sample | B6: 2023 | C6: 66 | D6: 21 | E6: 77 | F6: 38
A7: North Sample | B7: 2022 | C7: 62 | D7: 18 | E7: 74 | F7: 35
A8: River Sample | B8: 2024 | C8: 57 | D8: 18 | E8: 69 | F8: 33
A9: Coastal Sample | B9: 2024 | C9: 54 | D9: 16 | E9: 66 | F9: 31
A10: River Sample | B10: 2023 | C10: 52 | D10: 15 | E10: 65 | F10: 30
A11: Coastal Sample | B11: 2023 | C11: 49 | D11: 13 | E11: 62 | F11: 28
A12: River Sample | B12: 2022 | C12: 48 | D12: 12 | E12: 61 | F12: 27
A13: Coastal Sample | B13: 2022 | C13: 44 | D13: 10 | E13: 58 | F13: 24
A15: DATA STATUS: | B15: SYNTHETIC / ILLUSTRATIVE — NOT OFFICIAL DATA
A16: formulas
A17: =COUNTA(A2:A13) -> 12 | B17: Number of nonblank area labels
A18: =COUNT(B2:B13) -> 12 | B18: Number of numeric years
A19: =MIN(C2:C13) -> 44 | B19: Minimum access value
A20: =MAX(D2:D13) -> 35 | B20: Maximum access value

Sheet Day3_Practice
A1: Household_ID | B1: Monthly_Income_BDT | C1: Internet_Hours_Weekly | D1: Internet_Expense_BDT | E1: Income_Category
A2: H001 | B2: 18000 | C2: 8 | D2: 600 | E2: =IF(B2>=30000,"At/above 30,000","Below 30,000") -> Below 30,000
A3: H002 | B3: 25000 | C3: 12 | D3: 800 | E3: =IF(B3>=30000,"At/above 30,000","Below 30,000") -> Below 30,000 | H3: Functions | I3: Result | J3: Purpose
A4: H003 | B4: 32000 | C4: 18 | D4: 1000 | E4: =IF(B4>=30000,"At/above 30,000","Below 30,000") -> At/above 30,000 | H4: SUM | I4: =SUM(B2:B13) -> 367000 | J4: Add all numerical values together.
A5: H004 | B5: 22000 | C5: 10 | D5: 700 | E5: =IF(B5>=30000,"At/above 30,000","Below 30,000") -> Below 30,000 | H5: AVERAGE | I5: =AVERAGE(B2:B13) -> 30583.333 | J5: Calculate the arithmetic mean.
A6: H005 | B6: 45000 | C6: 25 | D6: 1500 | E6: =IF(B6>=30000,"At/above 30,000","Below 30,000") -> At/above 30,000 | H6: COUNT | I6: =COUNT(B2:B13) -> 12 | J6: Count cells containing numerical values.
A7: H006 | B7: 28000 | C7: 15 | D7: 900 | E7: =IF(B7>=30000,"At/above 30,000","Below 30,000") -> Below 30,000 | H7: MIN | I7: =MIN(B2:B13) -> 15000 | J7: Find the smallest numerical value.
A8: H007 | B8: 15000 | C8: 5 | D8: 500 | E8: =IF(B8>=30000,"At/above 30,000","Below 30,000") -> Below 30,000 | H8: MAX | I8: =MAX(B2:B13) -> 52000 | J8: Find the largest numerical value.
A9: H008 | B9: 36000 | C9: 20 | D9: 1200 | E9: =IF(B9>=30000,"At/above 30,000","Below 30,000") -> At/above 30,000 | H9: MEDIAN | I9: =MEDIAN(B2:B13) -> 29000 | J9: Find the middle value after sorting the observations.
A10: H009 | B10: 30000 | C10: 16 | D10: 1000 | E10: =IF(B10>=30000,"At/above 30,000","Below 30,000") -> At/above 30,000
A11: H010 | B11: 52000 | C11: 30 | D11: 1800 | E11: =IF(B11>=30000,"At/above 30,000","Below 30,000") -> At/above 30,000 | H11: The above functions are applied to the Column of Monthly_Income_BDT (cell B2 to B13) to generate different types of results. Similarly, we can apply these functions in other numerical cells to interpret various outcomes.
A12: H011 | B12: 24000 | C12: 11 | D12: 750 | E12: =IF(B12>=30000,"At/above 30,000","Below 30,000") -> Below 30,000
A13: H012 | B13: 40000 | C13: 22 | D13: 1300 | E13: =IF(B13>=30000,"At/above 30,000","Below 30,000") -> At/above 30,000
H16: IF Function | I16: The IF function allows Excel to make a decision based on a condition.
H17: For example, suppose we want to classify households according to whether their monthly income is at least BDT 30,000.
B18: Note: Synthetic practice data
H20: =IF(condition, value_if_true, value_if_false)
H21: =IF(B2>=30000,"At/above 30,000","Below 30,000")
H23: Result:
H24: The If function is applied to the cells from E2 to E13 under the Column 'Income_Category'. It represents the households whose income are below or at/above BDT 30000.

Sheet Day3_Summary
A1: Statistic | B1: Result
A2: Total household income | B2: =SUM(Day3_Practice!B2:B13) -> 367000
A3: Mean income | B3: =AVERAGE(Day3_Practice!B2:B13) -> 30583.333
A4: Number of households | B4: =COUNT(Day3_Practice!B2:B13) -> 12 | E4: Note: Synthetic practice data
A5: MInimum income | B5: =MIN(Day3_Practice!B2:B13) -> 15000
A6: Maximun income | B6: =MAX(Day3_Practice!B2:B13) -> 52000
A7: Median income | B7: =MEDIAN(Day3_Practice!B2:B13) -> 29000
A10: Interpretation:
A11: The practice dataset contains 12 fictional households. Their combined monthly income is BDT 367,000. Mean monthly income is approximately BDT 30,583, while median income is BDT 29,000. The lowest recorded income is BDT 15,000 and the highest is BDT 52,000. The difference between the mean and median indicates that the distribution's centre differs depending on the measure used. However, this small, fictional dataset cannot support conclusions about the income distribution of Bangladesh.
A17: Question 1: What does the range between the minimum and maximum tell you?
A18: Answer: The range of monthly income is BDT 37,000, calculated as the difference between the maximum income of BDT 52,000 and the minimum income of BDT 15,000. This indicates considerable variation between the lowest- and highest-income households in this practice dataset. However, the range alone is insufficient to determine the overall level of income inequality because it does not describe how income is distributed among all households.
A23: Question 2: Why are these results insufficient to estimate income inequality in Bangladesh?
A24: Answer: These results are insufficient to estimate income inequality in Bangladesh because the dataset is synthetic, contains only 12 fictional household observations, and is not representative of the country's population. Although the calculations demonstrate how to analyse income data, they cannot support conclusions about actual household income or national income inequality. A credible national estimate would require suitable real-world data and an appropriate sampling or survey design, along with measures such as the Gini coefficient or the Lorenz curve.

Sheet DATA
A1: ID | B1: Region | C1: Internet Users | D1: Monthly Income (BDT) | E1: Internet Access | H1: Conditional Formula | L1: Purpose
A2: 101 | B2: Dhaka | C2: 80 | D2: 30000 | E2: Yes | H2: SUMIF | I2: =SUMIF(criteria_range, criteria, sum_range) | L2: Add values only when a condition is met.
A3: 102 | B3: Chattogram | C3: 65 | D3: 24000 | E3: Yes
A4: 103 | B4: Rajshahi | C4: 45 | D4: 18000 | E4: No | H4: Exercise Questions | J4: Formula | M4: Result
A5: 104 | B5: Dhaka | C5: 90 | D5: 35000 | E5: Yes | G5: 1 | H5: Total income in Dhaka | J5: =SUMIF(b2:b11,"Dhaka",d2:d11) | M5: =SUMIF(B2:B11,"Dhaka",D2:D11) -> 97000
A6: 105 | B6: Khulna | C6: 55 | D6: 20000 | E6: No | G6: 2 | H6: Total income in Chattogram | J6: =SUMIF(B2:B11,"Chattogram",D2:D11) | M6: =SUMIF(B2:B11,"Chattogram",D2:D11) -> 69000
A7: 106 | B7: Chattogram | C7: 70 | D7: 26000 | E7: Yes | G7: 3 | H7: Total income for records with access | J7: =SUMIF(E2:E11,"Yes",D2:D11) | M7: =SUMIF(E2:E11,"Yes",D2:D11) -> 169000
A8: 107 | B8: Rajshahi | C8: 40 | D8: 16000 | E8: No
A9: 108 | B9: Dhaka | C9: 85 | D9: 32000 | E9: Yes | G9: 4 | H9: Total income above BDT 25,000 | J9: =SUMIF(D2:D11,">25000") | M9: =SUMIF(D2:D11,">25000") -> 123000
A10: 109 | B10: Khulna | C10: 60 | D10: 22000 | E10: Yes
A11: 110 | B11: Chattogram | C11: 50 | D11: 19000 | E11: No | G11: 5 | H11: total Internet Users for Dhaka | J11: =SUMIF(B2:B11,"Dhaka",C2:C11) | M11: =SUMIF(B2:B11,"Dhaka",C2:C11) -> 255
C13: Note: Synthetic practice data
B15: Conditional Formula | E15: Purpose | H15: Conditional Formula | L15: Purpose
B16: COUNTIF | C16: =COUNTIF(range, criteria) | E16: Count how many cells meet one condition. | H16: COUNTIFS | I16: =COUNTIFS(criteria_range1, criteria1,criteria_range2, criteria2) | L16: Count records that satisfy two or more conditions simultaneously.
B18: Exercise Questions | D18: Formula | F18: Result
A19: 1 | B19: How many Dhaka Records? | D19: =COUNTIF(B2:B11,"Dhaka") | F19: =COUNTIF(B2:B11,"Dhaka") -> 3 | H19: Exercise Questions | J19: Formula | M19: Result
A20: 2 | B20: How many people have internet access? | D20: =COUNTIF(E2:E11,"Yes") | F20: =COUNTIF(E2:E11,"Yes") -> 6 | G20: 1 | H20: count people who: - live in Chattogram, and - have internet access. | J20: =COUNTIFS(B2:B11,"Chattogram",E2:E11,"Yes") | M20: =COUNTIFS(B2:B11,"Chattogram",E2:E11,"Yes") -> 2
A22: 3 | B22: How many income values exceed 25000? | D22: =COUNTIF(D2:D11,">25000") | F22: =COUNTIF(D2:D11,">25000") -> 4
G23: 2 | H23: Dhaka records with internet access | J23: =COUNTIFS(B2:B11,"Dhaka",E2:E11,"Yes") | M23: =COUNTIFS(B2:B11,"Dhaka",E2:E11,"Yes") -> 3
A24: 4 | B24: How many records have no internet access? | D24: =COUNTIF(E2:E11,"No") | F24: =COUNTIF(E2:E11,"No") -> 4
G25: 3 | H25: Records with income above 20000 and access | J25: =COUNTIFS(D2:D11,">20000",E2:E11,"Yes") | M25: =COUNTIFS(D2:D11,">20000",E2:E11,"Yes") -> 6
A26: 5 | B26: How many people have monthly income below BDT 20,000? | D26: =COUNTIF(d2:d10,"<20000") | F26: =COUNTIF(D2:D10,"<20000") -> 2
G27: 4 | H27: Rajshahi records without access | J27: =COUNTIFS(B2:B11,"Rajshahi",E2:E11,"No") | M27: =COUNTIFS(B2:B11,"Rajshahi",E2:E11,"No") -> 2
B31: Conditional Formula | E31: Purpose | H31: Formula | L31: Purpose
B32: SUMIFS | C32: =SUMIFS(sum_range, criteria_range1, criteria1,criteria_range2, criteria2) | E32: Add values only when multiple conditions are satisfied. | H32: XLOOKUP | I32: =XLOOKUP(lookup_value,lookup_array,return_array, [if_not_found]) | L32: Find an ID or other identifier and return a related value from another column.
B35: Exercise Questions | D35: Formula | F35: Result | H35: Exercise Questions | J35: Formula | M35: Result
A36: 1 | B36: total monthly income of Chattogram records with internet access. | D36: =SUMIFS(D2:D11,B2:B11,"Chattogram",E2:E11,"Yes") | F36: =SUMIFS(D2:D11,B2:B11,"Chattogram",E2:E11,"Yes") -> 50000 | G36: 1 | H36: Income associated with ID 104 | J36: =XLOOKUP(104,A2:A11,D2:D11,"Not Found") | M36: =_xlfn.XLOOKUP(104,A2:A11,D2:D11,"Not Found") -> 35000
G38: 2 | H38: Find income for ID 101 | J38: =XLOOKUP(101,A2:A11,D2:D11,Null) | M38: {=_xlfn.XLOOKUP(101,A2:A11,D2:D11,Null)} -> 30000
A39: 2 | B39: Income in Dhaka with internet access | D39: =SUMIFS(D2:D11,B2:B11,"Dhaka",E2:E11,"Yes") | F39: =SUMIFS(D2:D11,B2:B11,"Dhaka",E2:E11,"Yes") -> 97000 | G39: 3 | H39: Find region for ID 106 | J39: =XLOOKUP(106,A2:A11,B2:B11,Null) | M39: {=_xlfn.XLOOKUP(106,A2:A11,B2:B11,Null)} -> Chattogram
G40: 4 | H40: Find internet-access status for ID 107 | J40: =XLOOKUP(107,A2:A11,E2:E11,Null) | M40: {=_xlfn.XLOOKUP(107,A2:A11,E2:E11,Null)} -> No
A41: 3 | B41: Income in Khulna without internet access | D41: =SUMIFS(D2:D11,B2:B11,"Khulna",E2:E11,"No") | F41: =SUMIFS(D2:D11,B2:B11,"Khulna",E2:E11,"No") -> 20000
A42: 4 | B42: Internet Users in Chattogram with access | D42: =SUMIFS(C2:C11,B2:B11,"Chattogram",E2:E11,"Yes") | F42: =SUMIFS(C2:C11,B2:B11,"Chattogram",E2:E11,"Yes") -> 135 | G42: 5 | H42: Search for nonexistent ID 999 | J42: =XLOOKUP(999,A2:A11,D2:D11,"Not Found") | M42: =_xlfn.XLOOKUP(999,A2:A11,D2:D11,"Not Found") -> Not Found

Sheet ANALYSIS
A1: Conditional Analysis of a Fictional Digital Connectivity Dataset
A2: Analysis Question | B2: Formula | C2: Result
A3: Number of records in Dhaka | B3: =COUNTIF(DATA!B2:B11,"Dhaka") | C3: =COUNTIF(DATA!B2:B11,"Dhaka") -> 3
A4: Total income in Dhaka | B4: =SUMIF(DATA!B2:B11,"Dhaka",DATA!D2:D11) | C4: =SUMIF(DATA!B2:B11,"Dhaka",DATA!D2:D11) -> 97000
A5: Number of Chattogram records with access | B5: =COUNTIFS(DATA!B2:B11,"Chattogram",DATA!E2:E11,"Yes") | C5: =COUNTIFS(DATA!B2:B11,"Chattogram",DATA!E2:E11,"Yes") -> 2
A6: Total income in Chattogram with access | B6: =SUMIFS(DATA!D2:D11,DATA!B2:B11,"Chattogram",DATA!E2:E11,"Yes") | C6: =SUMIFS(DATA!D2:D11,DATA!B2:B11,"Chattogram",DATA!E2:E11,"Yes") -> 50000
A7: Income associated with ID 104 | B7: =XLOOKUP(104,DATA!A2:A11,DATA!D2:D11) | C7: =_xlfn.XLOOKUP(104,DATA!A2:A11,DATA!D2:D11) -> 35000
A8: Total internet users in Dhaka | B8: =SUMIF(DATA!B2:B11,"Dhaka",DATA!C2:C11) | C8: =SUMIF(DATA!B2:B11,"Dhaka",DATA!C2:C11) -> 255
B10: Note: Synthetic practice data
A13: NOTES — What I Learned
A14: Today I learned to use COUNTIF and SUMIF for calculations based on one condition, COUNTIFS and SUMIFS for multiple conditions, and XLOOKUP to retrieve related information using an ID. I practised analysing regional income, internet users, and internet-access records, and learned to organise results separately from raw data. These skills will support future statistical analysis and research projects. Note: This is synthetic practice data, not official Bangladesh statistics.

Sheet Day5_Data
A1: Customer_ID | B1: Region | C1: Plan | D1: Monthly_Bill_BDT | E1: Monthly_Data_GB | F1: Status | G1: Acquisition_Channel
A2: C001 | B2: Dhaka | C2: Basic | D2: 800 | E2: 50 | F2: Active | G2: Referral
A3: C002 | B3: Dhaka | C3: Standard | D3: 1000 | E3: 100 | F3: Active | G3: Facebook
A4: C003 | B4: Chattogram | C4: Premium | D4: 1500 | E4: 200 | F4: Active | G4: Referral
A5: C004 | B5: Khulna | C5: Basic | D5: 800 | E5: 50 | F5: Cancelled | G5: Walk-in
A6: C005 | B6: Dhaka | C6: Premium | D6: 1500 | E6: 200 | F6: Active | G6: Facebook
A7: C006 | B7: Rajshahi | C7: Standard | D7: 1000 | E7: 100 | F7: Active | G7: Walk-in
A8: C007 | B8: Chattogram | C8: Basic | D8: 800 | E8: 50 | F8: Active | G8: Referral
A9: C008 | B9: Khulna | C9: Standard | D9: 1000 | E9: 100 | F9: Cancelled | G9: Facebook
A10: C009 | B10: Dhaka | C10: Basic | D10: 800 | E10: 50 | F10: Cancelled | G10: Walk-in
A11: C010 | B11: Rajshahi | C11: Premium | D11: 1500 | E11: 200 | F11: Active | G11: Referral
A12: C011 | B12: Chattogram | C12: Standard | D12: 1000 | E12: 100 | F12: Active | G12: Facebook
A13: C012 | B13: Dhaka | C13: Standard | D13: 1000 | E13: 100 | F13: Cancelled | G13: Referral
... A21: C020 | B21: Dhaka | C21: Premium | D21: 1500 | E21: 200 | F21: Active | G21: Walk-in

Sheet Pivot_Analysis
A1: Customer Analysis
A2: Section 1 - Customer status by region
A3: Research/Business Question: How many customers are Active and Cancelled in each region?
A4: Purpose: Compare customer status across region.
A6: Count of Customer_ID | B6: Status
A7: Region | B7: Active | C7: Cancelled | D7: Grand Total
A8: Chattogram | B8: 4 | C8: 1 | D8: 5
A9: Dhaka | B9: 5 | C9: 2 | D9: 7
A10: Khulna | B10: 2 | C10: 2 | D10: 4
A11: Rajshahi | B11: 3 | C11: 1 | D11: 4
A12: Grand Total | B12: 14 | C12: 6 | D12: 20
A14: Interpretation
A15: Finding: Dhaka has the highest total number of customers, while Dhaka and Khulna have the highest numbers of cancelled customers in the practice dataset.
A17: Interpretation: Customer distribution and cancellations vary across regions.
A18: Limitation: These counts alone do not explain why customers cancelled or establish actual regional ISP performance.
A22: Section 2 - Monthly bill value by plan
A23: Research/Business Question: Which plan has the highest total monthly bill value?
A24: Purpose: Compare the total bill value and customer count across plans.
A26: Plan | B26: Sum of Monthly_Bill_BDT | C26: Count of Customer_ID
A27: Basic | B27: 5600 | C27: 7
A28: Premium | B28: 9000 | C28: 6
A29: Standard | B29: 7000 | C29: 7
A30: Grand Total | B30: 21600 | C30: 20
A31: Interpretation
A32: Finding: The Premium plan has the highest total monthly bill value, at BDT 9,000, despite having six customers compared with seven each for Basic and Standard.
A34: Interpretation: The Premium plan's higher monthly bill per customer results in a larger total bill value in this practice dataset.
A36: Limitation: Total bill value is not the same as profit. The data do not include operating costs, discounts, collection failures, or actual business records.
A40: Section 3 - Acquisition channel
A41: Research/Business Question: Which acquisition channel has the highest average monthly bill?
A42: Purpose: Compare average bill value and customer count by channel.
A44: Acquisition_Channel | B44: Average of Monthly_Bill_BDT | C44: Count of Customer_ID
A45: Facebook | B45: 1014.2857 | C45: 7
A46: Referral | B46: 1128.5714 | C46: 7
A47: Walk-in | B47: 1100 | C47: 6
A48: Grand Total | B48: 1080 | C48: 20
A50: Interpretation
A51: Finding: Referral has the highest average monthly bill, approximately BDT 1,128.57 per customer, followed by Walk-in at BDT 1,100 and Facebook at BDT 1,014.29.
A53: Interpretation: In this practice dataset, customers acquired through referrals have a higher average monthly bill than customers acquired through the other two channels.
A55: Limitation: The sample is small and fictional. These averages do not establish which channel is most profitable, has the lowest acquisition cost, or retains customers longer.
